{"level":1061,"steps":[{"holeModels":[{"id":0,"hasScrew":1,"hasLock":0,"hasAdsHole":0,"hasIce":0,"hasKey":0,"screwPoolType":0,"hasLockKey":0,"x":0.8000128,"y":-1.5000267,"scaleX":0.4,"scaleY":0.4,"iceUnlockNumber":0,"hasLockNumberScrew":0,"numberLockIron":0},{"id":1,"hasScrew":1,"hasLock":0,"hasAdsHole":0,"hasIce":0,"hasKey":0,"screwPoolType":0,"hasLockKey":0,"x":-0.80001163,"y":-1.5000267,"scaleX":0.4,"scaleY":0.4,"iceUnlockNumber":0,"hasLockNumberScrew":0,"numberLockIron":0},{"id":2,"hasScrew":1,"hasLock":0,"hasAdsHole":0,"hasIce":0,"hasKey":0,"screwPoolType":0,"hasLockKey":0,"x":1.4000211,"y":0.09999752,"scaleX":0.4,"scaleY":0.4,"iceUnlockNumber":0,"hasLockNumberScrew":0,"numberLockIron":0},{"id":3,"hasScrew":1,"hasLock":0,"hasAdsHole":0,"hasIce":0,"hasKey":0,"screwPoolType":0,"hasLockKey":0,"x":-1.4000211,"y":0.099998,"scaleX":0.4,"scaleY":0.4,"iceUnlockNumber":0,"hasLockNumberScrew":0,"numberLockIron":0},{"id":4,"hasScrew":1,"hasLock":0,"hasAdsHole":0,"hasIce":0,"hasKey":0,"screwPoolType":0,"hasLockKey":0,"x":0.80001116,"y":2.0000267,"scaleX":0.4,"scaleY":0.4,"iceUnlockNumber":0,"hasLockNumberScrew":0,"numberLockIron":0},{"id":5,"hasScrew":1,"hasLock":0,"hasAdsHole":0,"hasIce":0,"hasKey":0,"screwPoolType":0,"hasLockKey":0,"x":0,"y":2.200029,"scaleX":0.4,"scaleY":0.4,"iceUnlockNumber":0,"hasLockNumberScrew":0,"numberLockIron":0},{"id":6,"hasScrew":1,"hasLock":0,"hasAdsHole":0,"hasIce":0,"hasKey":0,"screwPoolType":0,"hasLockKey":0,"x":-0.80001163,"y":2.0000248,"scaleX":0.4,"scaleY":0.4,"iceUnlockNumber":0,"hasLockNumberScrew":0,"numberLockIron":0},{"id":7,"hasScrew":0,"hasLock":0,"hasAdsHole":0,"hasIce":0,"hasKey":0,"screwPoolType":0,"hasLockKey":0,"x":-1.0000348,"y":3.2,"scaleX":0.4,"scaleY":0.4,"iceUnlockNumber":0,"hasLockNumberScrew":0,"numberLockIron":0},{"id":8,"hasScrew":1,"hasLock":0,"hasAdsHole":0,"hasIce":0,"hasKey":0,"screwPoolType":0,"hasLockKey":0,"x":1.6500239,"y":1.300015,"scaleX":0.4,"scaleY":0.4,"iceUnlockNumber":0,"hasLockNumberScrew":0,"numberLockIron":0},{"id":9,"hasScrew":1,"hasLock":0,"hasAdsHole":0,"hasIce":0,"hasKey":0,"screwPoolType":0,"hasLockKey":0,"x":-1.6500249,"y":1.3000159,"scaleX":0.4,"scaleY":0.4,"iceUnlockNumber":0,"hasLockNumberScrew":0,"numberLockIron":0},{"id":10,"hasScrew":0,"hasLock":0,"hasAdsHole":1,"hasIce":0,"hasKey":0,"screwPoolType":0,"hasLockKey":0,"x":0.000005722046,"y":3.2,"scaleX":0.4,"scaleY":0.4,"iceUnlockNumber":0,"hasLockNumberScrew":0,"numberLockIron":0},{"id":11,"hasScrew":0,"hasLock":0,"hasAdsHole":0,"hasIce":0,"hasKey":0,"screwPoolType":0,"hasLockKey":0,"x":1.0000429,"y":3.2,"scaleX":0.4,"scaleY":0.4,"iceUnlockNumber":0,"hasLockNumberScrew":0,"numberLockIron":0},{"id":12,"hasScrew":1,"hasLock":0,"hasAdsHole":0,"hasIce":0,"hasKey":0,"screwPoolType":0,"hasLockKey":0,"x":-0.4000039,"y":0.90000916,"scaleX":0.4,"scaleY":0.4,"iceUnlockNumber":0,"hasLockNumberScrew":0,"numberLockIron":0},{"id":13,"hasScrew":1,"hasLock":0,"hasAdsHole":0,"hasIce":0,"hasKey":0,"screwPoolType":0,"hasLockKey":0,"x":0.4000044,"y":0.90000916,"scaleX":0.4,"scaleY":0.4,"iceUnlockNumber":0,"hasLockNumberScrew":0,"numberLockIron":0},{"id":14,"hasScrew":1,"hasLock":0,"hasAdsHole":0,"hasIce":0,"hasKey":0,"screwPoolType":0,"hasLockKey":0,"x":0.25000167,"y":-0.9000068,"scaleX":0.4,"scaleY":0.4,"iceUnlockNumber":0,"hasLockNumberScrew":0,"numberLockIron":0},{"id":15,"hasScrew":1,"hasLock":0,"hasAdsHole":0,"hasIce":0,"hasKey":0,"screwPoolType":0,"hasLockKey":0,"x":-0.25000095,"y":-0.9000068,"scaleX":0.4,"scaleY":0.4,"iceUnlockNumber":0,"hasLockNumberScrew":0,"numberLockIron":0}],"itemBoomModels":[],"keyModels":[],"ironOverlayModels":[],"itemRopeModels":[],"boardIncreaseSize":0,"ironModels":[{"id":0,"layer":1,"layerPhysic":6,"orderLayer":5,"spriteName":"shape (38)","hasIce":0,"x":-0.3250041,"y":-1.2500229,"angle":167,"scaleX":0.4500009,"scaleY":0.4500009,"polygonColliderPoints":[{"x":0.625,"y":0.255},{"x":1.495,"y":0.305},{"x":1.7249999,"y":0.635},{"x":1.7249999,"y":0.955},{"x":1.405,"y":1.3249999},{"x":-1.525,"y":1.285},{"x":-1.7249999,"y":1.015},{"x":-1.7249999,"y":0.60499996},{"x":-1.5849999,"y":0.36499998},{"x":-1.285,"y":0.255},{"x":-0.615,"y":0.255},{"x":-0.545,"y":0.175},{"x":-0.525,"y":-0.995},{"x":-0.355,"y":-1.245},{"x":-0.03506273,"y":-1.3175836},{"x":0.19115032,"y":-1.2773006},{"x":0.4413939,"y":-1.119794},{"x":0.545,"y":-0.905},{"x":0.545,"y":0.205}]},{"id":1,"layer":2,"layerPhysic":7,"orderLayer":7,"spriteName":"shape (38)","hasIce":0,"x":0.32500458,"y":-1.2500238,"angle":193,"scaleX":0.4500003,"scaleY":0.4500003,"polygonColliderPoints":[{"x":0.625,"y":0.255},{"x":1.495,"y":0.305},{"x":1.7249999,"y":0.635},{"x":1.7249999,"y":0.955},{"x":1.405,"y":1.3249999},{"x":-1.525,"y":1.285},{"x":-1.7249999,"y":1.015},{"x":-1.7249999,"y":0.60499996},{"x":-1.5849999,"y":0.36499998},{"x":-1.285,"y":0.255},{"x":-0.615,"y":0.255},{"x":-0.545,"y":0.175},{"x":-0.525,"y":-0.995},{"x":-0.355,"y":-1.245},{"x":-0.03506273,"y":-1.3175836},{"x":0.19115032,"y":-1.2773006},{"x":0.4413939,"y":-1.119794},{"x":0.545,"y":-0.905},{"x":0.545,"y":0.205}]},{"id":2,"layer":3,"layerPhysic":14,"orderLayer":9,"spriteName":"shape (35)","hasIce":0,"x":4.7683716e-7,"y":-0.6000147,"angle":180,"scaleX":0.4499997,"scaleY":0.4499997,"polygonColliderPoints":[{"x":-0.91499996,"y":-0.655},{"x":-0.865,"y":-0.435},{"x":-0.66499996,"y":-0.145},{"x":-0.475,"y":0.015},{"x":-0.125,"y":0.13499999},{"x":0.125,"y":0.13499999},{"x":0.33499998,"y":0.085},{"x":0.575,"y":-0.055},{"x":0.755,"y":-0.24499999},{"x":0.895,"y":-0.525},{"x":0.935,"y":-0.885},{"x":1.185,"y":-1.2149999},{"x":1.275,"y":-1.265},{"x":1.355,"y":-1.275},{"x":1.765,"y":-1.235},{"x":2.055,"y":-0.91499996},{"x":2.0449998,"y":-0.415},{"x":1.985,"y":-0.114999995},{"x":1.685,"y":0.445},{"x":1.175,"y":0.935},{"x":0.72499996,"y":1.175},{"x":0.265,"y":1.275},{"x":-0.565,"y":1.225},{"x":-0.775,"y":1.145},{"x":-1.375,"y":0.765},{"x":-1.8149999,"y":0.225},{"x":-2.0449998,"y":-0.45499998},{"x":-2.055,"y":-0.525},{"x":-2.0449998,"y":-0.97499996},{"x":-1.9649999,"y":-1.105},{"x":-1.8249999,"y":-1.2149999},{"x":-1.735,"y":-1.255},{"x":-1.675,"y":-1.275},{"x":-1.245,"y":-1.255},{"x":-1.035,"y":-1.115}]},{"id":3,"layer":4,"layerPhysic":15,"orderLayer":11,"spriteName":"shape (35)","hasIce":0,"x":-0.67500925,"y":-1.1000209,"angle":224.9999,"scaleX":0.4500006,"scaleY":0.4500006,"polygonColliderPoints":[{"x":-0.91499996,"y":-0.655},{"x":-0.865,"y":-0.435},{"x":-0.66499996,"y":-0.145},{"x":-0.475,"y":0.015},{"x":-0.125,"y":0.13499999},{"x":0.125,"y":0.13499999},{"x":0.33499998,"y":0.085},{"x":0.575,"y":-0.055},{"x":0.755,"y":-0.24499999},{"x":0.895,"y":-0.525},{"x":0.935,"y":-0.885},{"x":1.185,"y":-1.2149999},{"x":1.275,"y":-1.265},{"x":1.355,"y":-1.275},{"x":1.765,"y":-1.235},{"x":2.055,"y":-0.91499996},{"x":2.0449998,"y":-0.415},{"x":1.985,"y":-0.114999995},{"x":1.685,"y":0.445},{"x":1.175,"y":0.935},{"x":0.72499996,"y":1.175},{"x":0.265,"y":1.275},{"x":-0.565,"y":1.225},{"x":-0.775,"y":1.145},{"x":-1.375,"y":0.765},{"x":-1.8149999,"y":0.225},{"x":-2.0449998,"y":-0.45499998},{"x":-2.055,"y":-0.525},{"x":-2.0449998,"y":-0.97499996},{"x":-1.9649999,"y":-1.105},{"x":-1.8249999,"y":-1.2149999},{"x":-1.735,"y":-1.255},{"x":-1.675,"y":-1.275},{"x":-1.245,"y":-1.255},{"x":-1.035,"y":-1.115}]},{"id":4,"layer":6,"layerPhysic":17,"orderLayer":15,"spriteName":"shape (35)","hasIce":0,"x":0.67500806,"y":-1.1000218,"angle":135.0001,"scaleX":0.4499996,"scaleY":0.4499996,"polygonColliderPoints":[{"x":-0.91499996,"y":-0.655},{"x":-0.865,"y":-0.435},{"x":-0.66499996,"y":-0.145},{"x":-0.475,"y":0.015},{"x":-0.125,"y":0.13499999},{"x":0.125,"y":0.13499999},{"x":0.33499998,"y":0.085},{"x":0.575,"y":-0.055},{"x":0.755,"y":-0.24499999},{"x":0.895,"y":-0.525},{"x":0.935,"y":-0.885},{"x":1.185,"y":-1.2149999},{"x":1.275,"y":-1.265},{"x":1.355,"y":-1.275},{"x":1.765,"y":-1.235},{"x":2.055,"y":-0.91499996},{"x":2.0449998,"y":-0.415},{"x":1.985,"y":-0.114999995},{"x":1.685,"y":0.445},{"x":1.175,"y":0.935},{"x":0.72499996,"y":1.175},{"x":0.265,"y":1.275},{"x":-0.565,"y":1.225},{"x":-0.775,"y":1.145},{"x":-1.375,"y":0.765},{"x":-1.8149999,"y":0.225},{"x":-2.0449998,"y":-0.45499998},{"x":-2.055,"y":-0.525},{"x":-2.0449998,"y":-0.97499996},{"x":-1.9649999,"y":-1.105},{"x":-1.8249999,"y":-1.2149999},{"x":-1.735,"y":-1.255},{"x":-1.675,"y":-1.275},{"x":-1.245,"y":-1.255},{"x":-1.035,"y":-1.115}]},{"id":5,"layer":1,"layerPhysic":6,"orderLayer":5,"spriteName":"bar","hasIce":0,"x":-1.525023,"y":0.70000696,"angle":101.7683,"scaleX":0.3451566,"scaleY":0.45,"polygonColliderPoints":[{"x":-2.485,"y":0.53999996},{"x":-2.565,"y":0.48},{"x":-2.565,"y":-0.53999996},{"x":2.565,"y":-0.53999996},{"x":2.565,"y":0.53},{"x":2.5349998,"y":0.53999996}]},{"id":6,"layer":1,"layerPhysic":6,"orderLayer":5,"spriteName":"bar","hasIce":0,"x":1.525023,"y":0.7000065,"angle":78.23177,"scaleX":0.3451567,"scaleY":0.45,"polygonColliderPoints":[{"x":-2.485,"y":0.53999996},{"x":-2.565,"y":0.48},{"x":-2.565,"y":-0.53999996},{"x":2.565,"y":-0.53999996},{"x":2.565,"y":0.53},{"x":2.5349998,"y":0.53999996}]},{"id":7,"layer":1,"layerPhysic":6,"orderLayer":5,"spriteName":"bar","hasIce":0,"x":0.600008,"y":1.4500179,"angle":70.016884,"scaleX":0.3340978,"scaleY":0.45,"polygonColliderPoints":[{"x":-2.485,"y":0.53999996},{"x":-2.565,"y":0.48},{"x":-2.565,"y":-0.53999996},{"x":2.565,"y":-0.53999996},{"x":2.565,"y":0.53},{"x":2.5349998,"y":0.53999996}]},{"id":8,"layer":1,"layerPhysic":6,"orderLayer":5,"spriteName":"bar","hasIce":0,"x":-0.60000753,"y":1.450017,"angle":109.9832,"scaleX":0.3340975,"scaleY":0.45,"polygonColliderPoints":[{"x":-2.485,"y":0.53999996},{"x":-2.565,"y":0.48},{"x":-2.565,"y":-0.53999996},{"x":2.565,"y":-0.53999996},{"x":2.565,"y":0.53},{"x":2.5349998,"y":0.53999996}]},{"id":9,"layer":2,"layerPhysic":7,"orderLayer":7,"spriteName":"bar","hasIce":0,"x":-1.225018,"y":1.6500201,"angle":219.4724,"scaleX":0.3202304,"scaleY":0.45,"polygonColliderPoints":[{"x":-2.485,"y":0.53999996},{"x":-2.565,"y":0.48},{"x":-2.565,"y":-0.53999996},{"x":2.565,"y":-0.53999996},{"x":2.565,"y":0.53},{"x":2.5349998,"y":0.53999996}]},{"id":10,"layer":2,"layerPhysic":7,"orderLayer":7,"spriteName":"bar","hasIce":0,"x":1.225018,"y":1.6500211,"angle":140.5275,"scaleX":0.3202305,"scaleY":0.45,"polygonColliderPoints":[{"x":-2.485,"y":0.53999996},{"x":-2.565,"y":0.48},{"x":-2.565,"y":-0.53999996},{"x":2.565,"y":-0.53999996},{"x":2.565,"y":0.53},{"x":2.5349998,"y":0.53999996}]},{"id":11,"layer":8,"layerPhysic":19,"orderLayer":19,"spriteName":"silver 2","hasIce":0,"x":-0.8250108,"y":-0.4000044,"angle":138.9913,"scaleX":0.4047987,"scaleY":0.45,"polygonColliderPoints":[{"x":-2.4363685,"y":0.53999996},{"x":-2.5511053,"y":0.40401322},{"x":-2.5498672,"y":-0.37077624},{"x":-2.43151,"y":-0.53592014},{"x":2.4284582,"y":-0.47191802},{"x":2.4913006,"y":-0.449712},{"x":2.5158255,"y":-0.36324117},{"x":2.5351708,"y":0.40336686},{"x":2.5016344,"y":0.4714166},{"x":2.4345713,"y":0.5232619}]},{"id":12,"layer":9,"layerPhysic":20,"orderLayer":21,"spriteName":"bar","hasIce":0,"x":0.8250115,"y":-0.40000486,"angle":41.00872,"scaleX":0.4047985,"scaleY":0.45,"polygonColliderPoints":[{"x":-2.4363685,"y":0.53999996},{"x":-2.5511053,"y":0.40401322},{"x":-2.5498672,"y":-0.37077624},{"x":-2.43151,"y":-0.53592014},{"x":2.4284582,"y":-0.47191802},{"x":2.4913006,"y":-0.449712},{"x":2.5158255,"y":-0.36324117},{"x":2.5351708,"y":0.40336686},{"x":2.5016344,"y":0.4714166},{"x":2.4345713,"y":0.5232619}]},{"id":13,"layer":3,"layerPhysic":14,"orderLayer":9,"spriteName":"shape (32)","hasIce":0,"x":0,"y":2.1,"angle":0,"scaleX":0.45,"scaleY":0.45,"polygonColliderPoints":[{"x":-0.77,"y":-1.56},{"x":-0.21,"y":-1.4599999},{"x":0.29,"y":-1.48},{"x":1.4499999,"y":-1.63},{"x":1.68,"y":-1.48},{"x":1.81,"y":-1.27},{"x":1.79,"y":-0.96},{"x":1.74,"y":-0.88},{"x":1.1899999,"y":-0.21},{"x":0.90999997,"y":0.21},{"x":0.79999995,"y":0.42},{"x":0.35,"y":1.51},{"x":0.13,"y":1.63},{"x":-0.17999999,"y":1.62},{"x":-0.31,"y":1.54},{"x":-0.48,"y":1.3299999},{"x":-0.78999996,"y":0.29},{"x":-0.93,"y":0.04},{"x":-1.37,"y":-0.48},{"x":-1.38,"y":-0.48},{"x":-1.75,"y":-0.88},{"x":-1.81,"y":-1.02},{"x":-1.79,"y":-1.3399999},{"x":-1.63,"y":-1.54},{"x":-1.4499999,"y":-1.63},{"x":-0.87,"y":-1.5799999}]}],"time":60},{"holeModels":[{"id":0,"hasScrew":1,"hasLock":0,"hasAdsHole":0,"hasIce":0,"hasKey":0,"screwPoolType":0,"hasLockKey":0,"x":9.536743e-7,"y":2.75001,"scaleX":0.4,"scaleY":0.4,"iceUnlockNumber":0,"hasLockNumberScrew":0,"numberLockIron":0},{"id":1,"hasScrew":1,"hasLock":0,"hasAdsHole":0,"hasIce":0,"hasKey":0,"screwPoolType":0,"hasLockKey":0,"x":0.5500035,"y":1.700005,"scaleX":0.4,"scaleY":0.4,"iceUnlockNumber":0,"hasLockNumberScrew":0,"numberLockIron":0},{"id":2,"hasScrew":1,"hasLock":0,"hasAdsHole":0,"hasIce":0,"hasKey":0,"screwPoolType":0,"hasLockKey":0,"x":-0.5500021,"y":1.700005,"scaleX":0.4,"scaleY":0.4,"iceUnlockNumber":0,"hasLockNumberScrew":0,"numberLockIron":0},{"id":3,"hasScrew":1,"hasLock":0,"hasAdsHole":0,"hasIce":0,"hasKey":0,"screwPoolType":0,"hasLockKey":0,"x":-1.600008,"y":2.4000092,"scaleX":0.4,"scaleY":0.4,"iceUnlockNumber":0,"hasLockNumberScrew":0,"numberLockIron":0},{"id":4,"hasScrew":1,"hasLock":0,"hasAdsHole":0,"hasIce":0,"hasKey":0,"screwPoolType":0,"hasLockKey":0,"x":-1.075005,"y":2.0500069,"scaleX":0.4,"scaleY":0.4,"iceUnlockNumber":0,"hasLockNumberScrew":0,"numberLockIron":0},{"id":5,"hasScrew":1,"hasLock":0,"hasAdsHole":0,"hasIce":0,"hasKey":0,"screwPoolType":0,"hasLockKey":0,"x":1.075007,"y":2.050006,"scaleX":0.4,"scaleY":0.4,"iceUnlockNumber":0,"hasLockNumberScrew":0,"numberLockIron":0},{"id":6,"hasScrew":1,"hasLock":0,"hasAdsHole":0,"hasIce":0,"hasKey":0,"screwPoolType":0,"hasLockKey":0,"x":0.5500028,"y":0.69999933,"scaleX":0.4,"scaleY":0.4,"iceUnlockNumber":0,"hasLockNumberScrew":0,"numberLockIron":0},{"id":7,"hasScrew":1,"hasLock":0,"hasAdsHole":0,"hasIce":0,"hasKey":0,"screwPoolType":0,"hasLockKey":0,"x":-0.55000305,"y":0.6999998,"scaleX":0.4,"scaleY":0.4,"iceUnlockNumber":0,"hasLockNumberScrew":0,"numberLockIron":0},{"id":8,"hasScrew":1,"hasLock":0,"hasAdsHole":0,"hasIce":0,"hasKey":0,"screwPoolType":0,"hasLockKey":0,"x":1.600008,"y":1.5000029,"scaleX":0.4,"scaleY":0.4,"iceUnlockNumber":0,"hasLockNumberScrew":0,"numberLockIron":0},{"id":9,"hasScrew":1,"hasLock":0,"hasAdsHole":0,"hasIce":0,"hasKey":0,"screwPoolType":0,"hasLockKey":0,"x":-1.600008,"y":1.5000048,"scaleX":0.4,"scaleY":0.4,"iceUnlockNumber":0,"hasLockNumberScrew":0,"numberLockIron":0},{"id":10,"hasScrew":1,"hasLock":0,"hasAdsHole":0,"hasIce":0,"hasKey":0,"screwPoolType":0,"hasLockKey":0,"x":-1.200007,"y":0.12999678,"scaleX":0.4,"scaleY":0.4,"iceUnlockNumber":0,"hasLockNumberScrew":0,"numberLockIron":0},{"id":11,"hasScrew":1,"hasLock":0,"hasAdsHole":0,"hasIce":0,"hasKey":0,"screwPoolType":0,"hasLockKey":0,"x":-0.5500035,"y":-0.44000578,"scaleX":0.4,"scaleY":0.4,"iceUnlockNumber":0,"hasLockNumberScrew":0,"numberLockIron":0},{"id":12,"hasScrew":1,"hasLock":0,"hasAdsHole":0,"hasIce":0,"hasKey":0,"screwPoolType":0,"hasLockKey":0,"x":0.5500021,"y":-0.44000626,"scaleX":0.4,"scaleY":0.4,"iceUnlockNumber":0,"hasLockNumberScrew":0,"numberLockIron":0},{"id":13,"hasScrew":1,"hasLock":0,"hasAdsHole":0,"hasIce":0,"hasKey":0,"screwPoolType":0,"hasLockKey":0,"x":1.200005,"y":0.12999582,"scaleX":0.4,"scaleY":0.4,"iceUnlockNumber":0,"hasLockNumberScrew":0,"numberLockIron":0},{"id":14,"hasScrew":1,"hasLock":0,"hasAdsHole":0,"hasIce":0,"hasKey":0,"screwPoolType":0,"hasLockKey":0,"x":-4.7683716e-7,"y":0.1299963,"scaleX":0.4,"scaleY":0.4,"iceUnlockNumber":0,"hasLockNumberScrew":0,"numberLockIron":0},{"id":15,"hasScrew":1,"hasLock":0,"hasAdsHole":0,"hasIce":0,"hasKey":0,"screwPoolType":0,"hasLockKey":0,"x":-0.0000014305115,"y":-1.4000111,"scaleX":0.4,"scaleY":0.4,"iceUnlockNumber":0,"hasLockNumberScrew":0,"numberLockIron":0},{"id":16,"hasScrew":1,"hasLock":0,"hasAdsHole":0,"hasIce":0,"hasKey":0,"screwPoolType":0,"hasLockKey":0,"x":-1.0000081,"y":-1.2000089,"scaleX":0.4,"scaleY":0.4,"iceUnlockNumber":0,"hasLockNumberScrew":0,"numberLockIron":0},{"id":17,"hasScrew":1,"hasLock":0,"hasAdsHole":0,"hasIce":0,"hasKey":0,"screwPoolType":0,"hasLockKey":0,"x":1.000005,"y":-1.2000113,"scaleX":0.4,"scaleY":0.4,"iceUnlockNumber":0,"hasLockNumberScrew":0,"numberLockIron":0},{"id":18,"hasScrew":0,"hasLock":0,"hasAdsHole":0,"hasIce":0,"hasKey":0,"screwPoolType":0,"hasLockKey":0,"x":-1,"y":3.2,"scaleX":0.4,"scaleY":0.4,"iceUnlockNumber":0,"hasLockNumberScrew":0,"numberLockIron":0},{"id":19,"hasScrew":0,"hasLock":0,"hasAdsHole":0,"hasIce":0,"hasKey":0,"screwPoolType":0,"hasLockKey":0,"x":1,"y":3.2,"scaleX":0.4,"scaleY":0.4,"iceUnlockNumber":0,"hasLockNumberScrew":0,"numberLockIron":0},{"id":20,"hasScrew":0,"hasLock":0,"hasAdsHole":0,"hasIce":0,"hasKey":0,"screwPoolType":0,"hasLockKey":0,"x":1.5999999,"y":3.2,"scaleX":0.4,"scaleY":0.4,"iceUnlockNumber":0,"hasLockNumberScrew":0,"numberLockIron":0},{"id":21,"hasScrew":1,"hasLock":1,"hasAdsHole":0,"hasIce":0,"hasKey":0,"screwPoolType":0,"hasLockKey":0,"x":1.600009,"y":2.4000082,"scaleX":0.4,"scaleY":0.4,"iceUnlockNumber":0,"hasLockNumberScrew":0,"numberLockIron":0},{"id":22,"hasScrew":0,"hasLock":0,"hasAdsHole":1,"hasIce":0,"hasKey":0,"screwPoolType":0,"hasLockKey":0,"x":-1.5999999,"y":3.2,"scaleX":0.4,"scaleY":0.4,"iceUnlockNumber":0,"hasLockNumberScrew":0,"numberLockIron":0},{"id":23,"hasScrew":1,"hasLock":0,"hasAdsHole":0,"hasIce":0,"hasKey":0,"screwPoolType":0,"hasLockKey":0,"x":0,"y":1.1999998,"scaleX":0.4,"scaleY":0.4,"iceUnlockNumber":0,"hasLockNumberScrew":0,"numberLockIron":0},{"id":24,"hasScrew":1,"hasLock":0,"hasAdsHole":0,"hasIce":0,"hasKey":0,"screwPoolType":0,"hasLockKey":0,"x":-1.7999997,"y":-0.5,"scaleX":0.4,"scaleY":0.4,"iceUnlockNumber":0,"hasLockNumberScrew":0,"numberLockIron":0},{"id":25,"hasScrew":1,"hasLock":0,"hasAdsHole":0,"hasIce":0,"hasKey":0,"screwPoolType":0,"hasLockKey":0,"x":1.8,"y":-0.5,"scaleX":0.4,"scaleY":0.4,"iceUnlockNumber":0,"hasLockNumberScrew":0,"numberLockIron":0},{"id":26,"hasScrew":1,"hasLock":0,"hasAdsHole":0,"hasIce":0,"hasKey":0,"screwPoolType":0,"hasLockKey":0,"x":-1.7999997,"y":0.099999905,"scaleX":0.4,"scaleY":0.4,"iceUnlockNumber":0,"hasLockNumberScrew":0,"numberLockIron":0},{"id":27,"hasScrew":1,"hasLock":0,"hasAdsHole":0,"hasIce":0,"hasKey":0,"screwPoolType":0,"hasLockKey":0,"x":1.8,"y":0.099999905,"scaleX":0.4,"scaleY":0.4,"iceUnlockNumber":0,"hasLockNumberScrew":0,"numberLockIron":0},{"id":28,"hasScrew":1,"hasLock":0,"hasAdsHole":0,"hasIce":0,"hasKey":0,"screwPoolType":0,"hasLockKey":0,"x":-1.7999997,"y":-1.6999998,"scaleX":0.4,"scaleY":0.4,"iceUnlockNumber":0,"hasLockNumberScrew":0,"numberLockIron":0},{"id":29,"hasScrew":1,"hasLock":0,"hasAdsHole":0,"hasIce":0,"hasKey":0,"screwPoolType":0,"hasLockKey":0,"x":1.8,"y":-1.6999998,"scaleX":0.4,"scaleY":0.4,"iceUnlockNumber":0,"hasLockNumberScrew":0,"numberLockIron":0},{"id":30,"hasScrew":1,"hasLock":0,"hasAdsHole":0,"hasIce":0,"hasKey":0,"screwPoolType":0,"hasLockKey":0,"x":0,"y":2.15,"scaleX":0.4,"scaleY":0.4,"iceUnlockNumber":0,"hasLockNumberScrew":0,"numberLockIron":0},{"id":31,"hasScrew":1,"hasLock":0,"hasAdsHole":0,"hasIce":0,"hasKey":0,"screwPoolType":0,"hasLockKey":0,"x":-0.8000002,"y":-1.8999996,"scaleX":0.4,"scaleY":0.4,"iceUnlockNumber":0,"hasLockNumberScrew":0,"numberLockIron":0},{"id":32,"hasScrew":1,"hasLock":0,"hasAdsHole":0,"hasIce":0,"hasKey":0,"screwPoolType":0,"hasLockKey":0,"x":0.79999995,"y":-1.8999996,"scaleX":0.4,"scaleY":0.4,"iceUnlockNumber":0,"hasLockNumberScrew":0,"numberLockIron":0}],"itemBoomModels":[],"keyModels":[{"id":0,"holeId":21,"x":2.1,"y":0.9000001,"scaleX":0.4499998,"scaleY":0.4499998,"angle":90}],"ironOverlayModels":[],"itemRopeModels":[],"boardIncreaseSize":0,"ironModels":[{"id":0,"layer":7,"layerPhysic":18,"orderLayer":17,"spriteName":"bar","hasIce":0,"x":0.8000052,"y":2.575009,"angle":167.6609,"scaleX":0.4448911,"scaleY":0.4500007,"polygonColliderPoints":[{"x":-2.4363685,"y":0.53999996},{"x":-2.5511053,"y":0.40401322},{"x":-2.5498672,"y":-0.37077624},{"x":-2.43151,"y":-0.53592014},{"x":2.4284582,"y":-0.47191802},{"x":2.4913006,"y":-0.449712},{"x":2.5158255,"y":-0.36324117},{"x":2.5351708,"y":0.40336686},{"x":2.5016344,"y":0.4714166},{"x":2.4345713,"y":0.5232619}]},{"id":1,"layer":8,"layerPhysic":19,"orderLayer":19,"spriteName":"silver 2","hasIce":0,"x":-0.8000035,"y":2.57501,"angle":192.339,"scaleX":0.4440238,"scaleY":0.4500014,"polygonColliderPoints":[{"x":-2.4363685,"y":0.53999996},{"x":-2.5511053,"y":0.40401322},{"x":-2.5498672,"y":-0.37077624},{"x":-2.43151,"y":-0.53592014},{"x":2.4284582,"y":-0.47191802},{"x":2.4913006,"y":-0.449712},{"x":2.5158255,"y":-0.36324117},{"x":2.5351708,"y":0.40336686},{"x":2.5016344,"y":0.4714166},{"x":2.4345713,"y":0.5232619}]},{"id":2,"layer":9,"layerPhysic":20,"orderLayer":21,"spriteName":"bar","hasIce":0,"x":-1.075005,"y":2.0500069,"angle":146.3099,"scaleX":0.3714746,"scaleY":0.4499996,"polygonColliderPoints":[{"x":-2.4363685,"y":0.53999996},{"x":-2.5511053,"y":0.40401322},{"x":-2.5498672,"y":-0.37077624},{"x":-2.43151,"y":-0.53592014},{"x":2.4284582,"y":-0.47191802},{"x":2.4913006,"y":-0.449712},{"x":2.5158255,"y":-0.36324117},{"x":2.5351708,"y":0.40336686},{"x":2.5016344,"y":0.4714166},{"x":2.4345713,"y":0.5232619}]},{"id":3,"layer":3,"layerPhysic":14,"orderLayer":9,"spriteName":"bar","hasIce":0,"x":1.075006,"y":2.050006,"angle":213.6901,"scaleX":0.3714745,"scaleY":0.4499997,"polygonColliderPoints":[{"x":-2.4363685,"y":0.53999996},{"x":-2.5511053,"y":0.40401322},{"x":-2.5498672,"y":-0.37077624},{"x":-2.43151,"y":-0.53592014},{"x":2.4284582,"y":-0.47191802},{"x":2.4913006,"y":-0.449712},{"x":2.5158255,"y":-0.36324117},{"x":2.5351708,"y":0.40336686},{"x":2.5016344,"y":0.4714166},{"x":2.4345713,"y":0.5232619}]},{"id":4,"layer":7,"layerPhysic":18,"orderLayer":17,"spriteName":"#4","hasIce":0,"x":4.7683716e-7,"y":1.7000122,"angle":180,"scaleX":0.4999999,"scaleY":0.4999999,"polygonColliderPoints":[{"x":-0.39,"y":-0.42999998},{"x":0.38,"y":-0.42999998},{"x":0.42,"y":-0.5},{"x":0.58,"y":-0.65999997},{"x":0.75,"y":-0.74},{"x":0.85999995,"y":-0.78},{"x":1.1999999,"y":-0.78},{"x":1.3399999,"y":-0.75},{"x":1.49,"y":-0.65999997},{"x":1.67,"y":-0.5},{"x":1.78,"y":-0.32},{"x":1.8199999,"y":-0.17},{"x":1.8199999,"y":0.14999999},{"x":1.81,"y":0.24},{"x":1.73,"y":0.42},{"x":1.5899999,"y":0.58},{"x":1.48,"y":0.68},{"x":1.26,"y":0.78},{"x":0.84,"y":0.78},{"x":0.71,"y":0.74},{"x":0.56,"y":0.64},{"x":0.37,"y":0.45},{"x":-0.39,"y":0.44},{"x":-0.45999998,"y":0.53999996},{"x":-0.61,"y":0.68},{"x":-0.74,"y":0.75},{"x":-0.84999996,"y":0.78},{"x":-1.27,"y":0.78},{"x":-1.48,"y":0.7},{"x":-1.7199999,"y":0.45},{"x":-1.8199999,"y":0.22999999},{"x":-1.8199999,"y":-0.17999999},{"x":-1.78,"y":-0.34},{"x":-1.68,"y":-0.5},{"x":-1.51,"y":-0.65999997},{"x":-1.3399999,"y":-0.74},{"x":-1.24,"y":-0.78},{"x":-0.89,"y":-0.78},{"x":-0.75,"y":-0.74},{"x":-0.59999996,"y":-0.65999997},{"x":-0.42999998,"y":-0.5}]},{"id":5,"layer":4,"layerPhysic":15,"orderLayer":11,"spriteName":"bar","hasIce":0,"x":-1.600008,"y":1.950007,"angle":89.99995,"scaleX":0.3007821,"scaleY":0.4500012,"polygonColliderPoints":[{"x":-2.4363685,"y":0.53999996},{"x":-2.5511053,"y":0.40401322},{"x":-2.5498672,"y":-0.37077624},{"x":-2.43151,"y":-0.53592014},{"x":2.4284582,"y":-0.47191802},{"x":2.4913006,"y":-0.449712},{"x":2.5158255,"y":-0.36324117},{"x":2.5351708,"y":0.40336686},{"x":2.5016344,"y":0.4714166},{"x":2.4345713,"y":0.5232619}]},{"id":6,"layer":3,"layerPhysic":14,"orderLayer":9,"spriteName":"bar","hasIce":0,"x":-1.075005,"y":1.6000051,"angle":190.7843,"scaleX":0.3337665,"scaleY":0.4500002,"polygonColliderPoints":[{"x":-2.4363685,"y":0.53999996},{"x":-2.5511053,"y":0.40401322},{"x":-2.5498672,"y":-0.37077624},{"x":-2.43151,"y":-0.53592014},{"x":2.4284582,"y":-0.47191802},{"x":2.4913006,"y":-0.449712},{"x":2.5158255,"y":-0.36324117},{"x":2.5351708,"y":0.40336686},{"x":2.5016344,"y":0.4714166},{"x":2.4345713,"y":0.5232619}]},{"id":7,"layer":8,"layerPhysic":19,"orderLayer":19,"spriteName":"silver 2","hasIce":0,"x":-1.075006,"y":1.1000023,"angle":142.696,"scaleX":0.3820753,"scaleY":0.4499999,"polygonColliderPoints":[{"x":-2.4363685,"y":0.53999996},{"x":-2.5511053,"y":0.40401322},{"x":-2.5498672,"y":-0.37077624},{"x":-2.43151,"y":-0.53592014},{"x":2.4284582,"y":-0.47191802},{"x":2.4913006,"y":-0.449712},{"x":2.5158255,"y":-0.36324117},{"x":2.5351708,"y":0.40336686},{"x":2.5016344,"y":0.4714166},{"x":2.4345713,"y":0.5232619}]},{"id":8,"layer":2,"layerPhysic":7,"orderLayer":7,"spriteName":"bar","hasIce":0,"x":1.075006,"y":1.6000042,"angle":169.2156,"scaleX":0.3337665,"scaleY":0.4500008,"polygonColliderPoints":[{"x":-2.4363685,"y":0.53999996},{"x":-2.5511053,"y":0.40401322},{"x":-2.5498672,"y":-0.37077624},{"x":-2.43151,"y":-0.53592014},{"x":2.4284582,"y":-0.47191802},{"x":2.4913006,"y":-0.449712},{"x":2.5158255,"y":-0.36324117},{"x":2.5351708,"y":0.40336686},{"x":2.5016344,"y":0.4714166},{"x":2.4345713,"y":0.5232619}]},{"id":9,"layer":5,"layerPhysic":16,"orderLayer":13,"spriteName":"bar","hasIce":0,"x":0.53750396,"y":2.4000082,"angle":146.9293,"scaleX":0.3755521,"scaleY":0.4500012,"polygonColliderPoints":[{"x":-2.4363685,"y":0.53999996},{"x":-2.5511053,"y":0.40401322},{"x":-2.5498672,"y":-0.37077624},{"x":-2.43151,"y":-0.53592014},{"x":2.4284582,"y":-0.47191802},{"x":2.4913006,"y":-0.449712},{"x":2.5158255,"y":-0.36324117},{"x":2.5351708,"y":0.40336686},{"x":2.5016344,"y":0.4714166},{"x":2.4345713,"y":0.5232619}]},{"id":10,"layer":6,"layerPhysic":17,"orderLayer":15,"spriteName":"bar","hasIce":0,"x":-0.5375018,"y":2.4000082,"angle":213.0706,"scaleX":0.3755518,"scaleY":0.4500005,"polygonColliderPoints":[{"x":-2.4363685,"y":0.53999996},{"x":-2.5511053,"y":0.40401322},{"x":-2.5498672,"y":-0.37077624},{"x":-2.43151,"y":-0.53592014},{"x":2.4284582,"y":-0.47191802},{"x":2.4913006,"y":-0.449712},{"x":2.5158255,"y":-0.36324117},{"x":2.5351708,"y":0.40336686},{"x":2.5016344,"y":0.4714166},{"x":2.4345713,"y":0.5232619}]},{"id":11,"layer":4,"layerPhysic":15,"orderLayer":11,"spriteName":"L_1","hasIce":0,"x":0.8500104,"y":0.1299901,"angle":0.00001327778,"scaleX":0.45,"scaleY":0.45,"polygonColliderPoints":[{"x":-1.3,"y":1.8399999},{"x":-1.2853657,"y":0.9065438},{"x":-1.2304872,"y":0.81463563},{"x":-1.1445128,"y":0.75978124},{"x":0.11975573,"y":0.73805124},{"x":0.20589104,"y":0.66269934},{"x":0.20569038,"y":-0.6228243},{"x":0.16951764,"y":-0.7077132},{"x":0.0926802,"y":-0.7605808},{"x":-1.1289208,"y":-0.7614388},{"x":-1.2016362,"y":-0.79085183},{"x":-1.266331,"y":-0.8806474},{"x":-1.2729138,"y":-1.6643006},{"x":-1.232108,"y":-1.73914},{"x":-1.1080441,"y":-1.8235413},{"x":1.1337378,"y":-1.8263577},{"x":1.2785622,"y":-1.6776357},{"x":1.2833079,"y":1.6895676},{"x":1.1606039,"y":1.8138351}]},{"id":12,"layer":1,"layerPhysic":6,"orderLayer":5,"spriteName":"L_1","hasIce":0,"x":-0.85001135,"y":0.12999249,"angle":180,"scaleX":0.4500004,"scaleY":0.4500004,"polygonColliderPoints":[{"x":-1.1151716,"y":1.8170453},{"x":-1.2841911,"y":1.7040439},{"x":-1.2853657,"y":0.9065438},{"x":-1.2304872,"y":0.81463563},{"x":-1.1445128,"y":0.75978124},{"x":0.11975573,"y":0.73805124},{"x":0.20589104,"y":0.66269934},{"x":0.20569038,"y":-0.6228243},{"x":0.16951764,"y":-0.7077132},{"x":0.0926802,"y":-0.7605808},{"x":-1.1289208,"y":-0.7614388},{"x":-1.2016362,"y":-0.79085183},{"x":-1.266331,"y":-0.8806474},{"x":-1.2729138,"y":-1.6643006},{"x":-1.232108,"y":-1.73914},{"x":-1.1080441,"y":-1.8235413},{"x":1.1337378,"y":-1.8263577},{"x":1.2785622,"y":-1.6776357},{"x":1.2833079,"y":1.6895676},{"x":1.1606039,"y":1.8138351}]},{"id":13,"layer":6,"layerPhysic":17,"orderLayer":15,"spriteName":"bar","hasIce":0,"x":-4.7683716e-7,"y":0.12999678,"angle":133.9769,"scaleX":0.4344102,"scaleY":0.4500007,"polygonColliderPoints":[{"x":-2.4363685,"y":0.53999996},{"x":-2.5511053,"y":0.40401322},{"x":-2.5498672,"y":-0.37077624},{"x":-2.43151,"y":-0.53592014},{"x":2.4284582,"y":-0.47191802},{"x":2.4913006,"y":-0.449712},{"x":2.5158255,"y":-0.36324117},{"x":2.5351708,"y":0.40336686},{"x":2.5016344,"y":0.4714166},{"x":2.4345713,"y":0.5232619}]},{"id":14,"layer":7,"layerPhysic":18,"orderLayer":17,"spriteName":"bar","hasIce":0,"x":-4.7683716e-7,"y":0.12999678,"angle":226.023,"scaleX":0.4344101,"scaleY":0.4500006,"polygonColliderPoints":[{"x":-2.4363685,"y":0.53999996},{"x":-2.5511053,"y":0.40401322},{"x":-2.5498672,"y":-0.37077624},{"x":-2.43151,"y":-0.53592014},{"x":2.4284582,"y":-0.47191802},{"x":2.4913006,"y":-0.449712},{"x":2.5158255,"y":-0.36324117},{"x":2.5351708,"y":0.40336686},{"x":2.5016344,"y":0.4714166},{"x":2.4345713,"y":0.5232619}]},{"id":15,"layer":9,"layerPhysic":20,"orderLayer":21,"spriteName":"Solid_Circle_3","hasIce":0,"x":-4.7683716e-7,"y":-1.4000273,"angle":180,"scaleX":0.8499999,"scaleY":0.8499999,"polygonColliderPoints":[{"x":0.45552891,"y":0.26812398},{"x":0.3846335,"y":0.3621542},{"x":0.2676116,"y":0.4560413},{"x":0.15078515,"y":0.51051235},{"x":0.07539319,"y":0.5340945},{"x":-0.18079714,"y":0.4932123},{"x":-0.31760857,"y":0.41321233},{"x":-0.42961335,"y":0.28480673},{"x":-0.48798552,"y":0.19400842},{"x":-0.5256038,"y":0.019637242},{"x":-0.51120764,"y":-0.13920286},{"x":-0.42840573,"y":-0.2932124},{"x":-0.30359903,"y":-0.42241523},{"x":-0.16519332,"y":-0.4932124},{"x":-0.07105205,"y":-0.5066472},{"x":0.15041047,"y":-0.46442005},{"x":0.30881616,"y":-0.39722195},{"x":0.46801904,"y":-0.2323914},{"x":0.52180284,"y":-0.07864271},{"x":0.5148066,"y":0.08123149}]},{"id":16,"layer":1,"layerPhysic":6,"orderLayer":5,"spriteName":"bar","hasIce":0,"x":1.400007,"y":0.8149996,"angle":253.7237,"scaleX":0.4037515,"scaleY":0.4500003,"polygonColliderPoints":[{"x":-2.4363685,"y":0.53999996},{"x":-2.5511053,"y":0.40401322},{"x":-2.5498672,"y":-0.37077624},{"x":-2.4434211,"y":-0.5248026},{"x":2.4376051,"y":-0.51033485},{"x":2.5034964,"y":-0.46678618},{"x":2.543266,"y":-0.39738947},{"x":2.5504155,"y":0.3948298},{"x":2.5016344,"y":0.4714166},{"x":2.4345713,"y":0.5232619}]},{"id":17,"layer":7,"layerPhysic":18,"orderLayer":17,"spriteName":"bar","hasIce":0,"x":-1.4000077,"y":0.81500053,"angle":106.2762,"scaleX":0.4037516,"scaleY":0.4499997,"polygonColliderPoints":[{"x":-2.4363685,"y":0.53999996},{"x":-2.5511053,"y":0.40401322},{"x":-2.5498672,"y":-0.37077624},{"x":-2.43151,"y":-0.53592014},{"x":2.4284582,"y":-0.47191802},{"x":2.4913006,"y":-0.449712},{"x":2.5158255,"y":-0.36324117},{"x":2.5351708,"y":0.40336686},{"x":2.5016344,"y":0.4714166},{"x":2.4345713,"y":0.5232619}]},{"id":18,"layer":9,"layerPhysic":20,"orderLayer":21,"spriteName":"bar","hasIce":0,"x":-1.100007,"y":-0.53500605,"angle":98.55177,"scaleX":0.3876877,"scaleY":0.4500006,"polygonColliderPoints":[{"x":-2.4363685,"y":0.53999996},{"x":-2.5511053,"y":0.40401322},{"x":-2.5498672,"y":-0.37077624},{"x":-2.43151,"y":-0.53592014},{"x":2.4284582,"y":-0.47191802},{"x":2.4913006,"y":-0.449712},{"x":2.5158255,"y":-0.36324117},{"x":2.5351708,"y":0.40336686},{"x":2.5016344,"y":0.4714166},{"x":2.4345713,"y":0.5232619}]},{"id":19,"layer":7,"layerPhysic":18,"orderLayer":17,"spriteName":"bar","hasIce":0,"x":1.1000051,"y":-0.5350075,"angle":261.4482,"scaleX":0.3876876,"scaleY":0.45,"polygonColliderPoints":[{"x":-2.4363685,"y":0.53999996},{"x":-2.5511053,"y":0.40401322},{"x":-2.5498672,"y":-0.37077624},{"x":-2.43151,"y":-0.53592014},{"x":2.4284582,"y":-0.47191802},{"x":2.4913006,"y":-0.449712},{"x":2.5158255,"y":-0.36324117},{"x":2.5351708,"y":0.40336686},{"x":2.5016344,"y":0.4714166},{"x":2.4345713,"y":0.5232619}]},{"id":20,"layer":6,"layerPhysic":17,"orderLayer":15,"spriteName":"bar","hasIce":0,"x":-0.5000043,"y":-1.3000097,"angle":168.69,"scaleX":0.3241817,"scaleY":0.4499997,"polygonColliderPoints":[{"x":-2.4363685,"y":0.53999996},{"x":-2.5511053,"y":0.40401322},{"x":-2.5498672,"y":-0.37077624},{"x":-2.43151,"y":-0.53592014},{"x":2.4284582,"y":-0.47191802},{"x":2.4913006,"y":-0.449712},{"x":2.5158255,"y":-0.36324117},{"x":2.5351708,"y":0.40336686},{"x":2.5016344,"y":0.4714166},{"x":2.4345713,"y":0.5232619}]},{"id":21,"layer":3,"layerPhysic":14,"orderLayer":9,"spriteName":"bar","hasIce":0,"x":0.50000167,"y":-1.3000112,"angle":191.3098,"scaleX":0.3241816,"scaleY":0.4500012,"polygonColliderPoints":[{"x":-2.4363685,"y":0.53999996},{"x":-2.5511053,"y":0.40401322},{"x":-2.5498672,"y":-0.37077624},{"x":-2.43151,"y":-0.53592014},{"x":2.4284582,"y":-0.47191802},{"x":2.4913006,"y":-0.449712},{"x":2.5158255,"y":-0.36324117},{"x":2.5351708,"y":0.40336686},{"x":2.5016344,"y":0.4714166},{"x":2.4345713,"y":0.5232619}]},{"id":22,"layer":3,"layerPhysic":14,"orderLayer":9,"spriteName":"bar","hasIce":0,"x":0.6000025,"y":0.1299963,"angle":180,"scaleX":0.3593761,"scaleY":0.4500004,"polygonColliderPoints":[{"x":-2.4363685,"y":0.53999996},{"x":-2.5511053,"y":0.40401322},{"x":-2.5498672,"y":-0.37077624},{"x":-2.43151,"y":-0.53592014},{"x":2.4284582,"y":-0.47191802},{"x":2.4913006,"y":-0.449712},{"x":2.5158255,"y":-0.36324117},{"x":2.5351708,"y":0.40336686},{"x":2.5016344,"y":0.4714166},{"x":2.4345713,"y":0.5232619}]},{"id":23,"layer":4,"layerPhysic":15,"orderLayer":11,"spriteName":"bar","hasIce":0,"x":-0.6000037,"y":0.12999678,"angle":180,"scaleX":0.3593763,"scaleY":0.4500004,"polygonColliderPoints":[{"x":-2.4363685,"y":0.53999996},{"x":-2.5511053,"y":0.40401322},{"x":-2.5498672,"y":-0.37077624},{"x":-2.43151,"y":-0.53592014},{"x":2.4284582,"y":-0.47191802},{"x":2.4913006,"y":-0.449712},{"x":2.5158255,"y":-0.36324117},{"x":2.5351708,"y":0.40336686},{"x":2.5016344,"y":0.4714166},{"x":2.4345713,"y":0.5232619}]},{"id":24,"layer":8,"layerPhysic":19,"orderLayer":19,"spriteName":"silver 2","hasIce":0,"x":-0.27500248,"y":-0.9200077,"angle":119.8091,"scaleX":0.3404281,"scaleY":0.4500012,"polygonColliderPoints":[{"x":-2.4363685,"y":0.53999996},{"x":-2.5511053,"y":0.40401322},{"x":-2.5498672,"y":-0.37077624},{"x":-2.43151,"y":-0.53592014},{"x":2.4284582,"y":-0.47191802},{"x":2.4913006,"y":-0.449712},{"x":2.5158255,"y":-0.36324117},{"x":2.5351708,"y":0.40336686},{"x":2.5016344,"y":0.4714166},{"x":2.4345713,"y":0.5232619}]},{"id":25,"layer":2,"layerPhysic":7,"orderLayer":7,"spriteName":"bar","hasIce":0,"x":0.27500057,"y":-0.92000866,"angle":240.1908,"scaleX":0.341093,"scaleY":0.4500001,"polygonColliderPoints":[{"x":-2.4363685,"y":0.53999996},{"x":-2.5511053,"y":0.40401322},{"x":-2.5498672,"y":-0.37077624},{"x":-2.43151,"y":-0.53592014},{"x":2.4284582,"y":-0.47191802},{"x":2.4913006,"y":-0.449712},{"x":2.5158255,"y":-0.36324117},{"x":2.5351708,"y":0.40336686},{"x":2.5016344,"y":0.4714166},{"x":2.4345713,"y":0.5232619}]},{"id":26,"layer":5,"layerPhysic":16,"orderLayer":13,"spriteName":"bar","hasIce":0,"x":-0.7750058,"y":-0.82000685,"angle":239.3699,"scaleX":0.2975073,"scaleY":0.4499994,"polygonColliderPoints":[{"x":-2.4363685,"y":0.53999996},{"x":-2.5511053,"y":0.40401322},{"x":-2.5498672,"y":-0.37077624},{"x":-2.43151,"y":-0.53592014},{"x":2.4284582,"y":-0.47191802},{"x":2.4913006,"y":-0.449712},{"x":2.5158255,"y":-0.36324117},{"x":2.5351708,"y":0.40336686},{"x":2.5016344,"y":0.4714166},{"x":2.4345713,"y":0.5232619}]},{"id":27,"layer":1,"layerPhysic":6,"orderLayer":5,"spriteName":"bar","hasIce":0,"x":0.77500343,"y":-0.82000923,"angle":120.63,"scaleX":0.2975074,"scaleY":0.4500003,"polygonColliderPoints":[{"x":-2.4363685,"y":0.53999996},{"x":-2.5511053,"y":0.40401322},{"x":-2.5498672,"y":-0.37077624},{"x":-2.4434211,"y":-0.5248026},{"x":2.4376051,"y":-0.51033485},{"x":2.5034964,"y":-0.46678618},{"x":2.543266,"y":-0.39738947},{"x":2.5504155,"y":0.3948298},{"x":2.5016344,"y":0.4714166},{"x":2.4345713,"y":0.5232619}]},{"id":28,"layer":2,"layerPhysic":7,"orderLayer":7,"spriteName":"bar","hasIce":0,"x":4.7683716e-7,"y":1.2000017,"angle":317.7263,"scaleX":0.4153545,"scaleY":0.45,"polygonColliderPoints":[{"x":-2.4363685,"y":0.53999996},{"x":-2.5511053,"y":0.40401322},{"x":-2.5498672,"y":-0.37077624},{"x":-2.43151,"y":-0.53592014},{"x":2.4284582,"y":-0.47191802},{"x":2.4913006,"y":-0.449712},{"x":2.5158255,"y":-0.36324117},{"x":2.5351708,"y":0.40336686},{"x":2.5016344,"y":0.4714166},{"x":2.4345713,"y":0.5232619}]},{"id":29,"layer":8,"layerPhysic":19,"orderLayer":19,"spriteName":"silver 2","hasIce":0,"x":1.075006,"y":1.1000009,"angle":37.303932,"scaleX":0.382075,"scaleY":0.45,"polygonColliderPoints":[{"x":-2.4363685,"y":0.53999996},{"x":-2.5511053,"y":0.40401322},{"x":-2.5498672,"y":-0.37077624},{"x":-2.43151,"y":-0.53592014},{"x":2.4284582,"y":-0.47191802},{"x":2.4913006,"y":-0.449712},{"x":2.5158255,"y":-0.36324117},{"x":2.5351708,"y":0.40336686},{"x":2.5016344,"y":0.4714166},{"x":2.4345713,"y":0.5232619}]},{"id":30,"layer":3,"layerPhysic":14,"orderLayer":9,"spriteName":"bar","hasIce":0,"x":0,"y":0.69999933,"angle":-0.00003415076,"scaleX":0.3398449,"scaleY":0.45,"polygonColliderPoints":[{"x":-2.4363685,"y":0.53999996},{"x":-2.5511053,"y":0.40401322},{"x":-2.5498672,"y":-0.37077624},{"x":-2.43151,"y":-0.53592014},{"x":2.4284582,"y":-0.47191802},{"x":2.4913006,"y":-0.449712},{"x":2.5158255,"y":-0.36324117},{"x":2.5351708,"y":0.40336686},{"x":2.5016344,"y":0.4714166},{"x":2.4345713,"y":0.5232619}]},{"id":31,"layer":5,"layerPhysic":16,"orderLayer":13,"spriteName":"bar","hasIce":0,"x":4.7683716e-7,"y":1.2000017,"angle":42.27367,"scaleX":0.4153545,"scaleY":0.4500002,"polygonColliderPoints":[{"x":-2.4363685,"y":0.53999996},{"x":-2.5511053,"y":0.40401322},{"x":-2.5498672,"y":-0.37077624},{"x":-2.43151,"y":-0.53592014},{"x":2.4284582,"y":-0.47191802},{"x":2.4913006,"y":-0.449712},{"x":2.5158255,"y":-0.36324117},{"x":2.5351708,"y":0.40336686},{"x":2.5016344,"y":0.4714166},{"x":2.4345713,"y":0.5232619}]},{"id":32,"layer":4,"layerPhysic":15,"orderLayer":11,"spriteName":"bar","hasIce":0,"x":1.600009,"y":1.950005,"angle":270,"scaleX":0.3007822,"scaleY":0.45,"polygonColliderPoints":[{"x":-2.4363685,"y":0.53999996},{"x":-2.5511053,"y":0.40401322},{"x":-2.5498672,"y":-0.37077624},{"x":-2.43151,"y":-0.53592014},{"x":2.4284582,"y":-0.47191802},{"x":2.4913006,"y":-0.449712},{"x":2.5158255,"y":-0.36324117},{"x":2.5351708,"y":0.40336686},{"x":2.5016344,"y":0.4714166},{"x":2.4345713,"y":0.5232619}]},{"id":33,"layer":6,"layerPhysic":17,"orderLayer":15,"spriteName":"bar","hasIce":0,"x":-1.7999997,"y":-0.20000029,"angle":90,"scaleX":0.2421875,"scaleY":0.45,"polygonColliderPoints":[{"x":-2.4363685,"y":0.53999996},{"x":-2.5511053,"y":0.40401322},{"x":-2.5498672,"y":-0.37077624},{"x":-2.43151,"y":-0.53592014},{"x":2.4284582,"y":-0.47191802},{"x":2.4913006,"y":-0.449712},{"x":2.5158255,"y":-0.36324117},{"x":2.5351708,"y":0.40336686},{"x":2.5016344,"y":0.4714166},{"x":2.4345713,"y":0.5232619}]},{"id":34,"layer":6,"layerPhysic":17,"orderLayer":15,"spriteName":"bar","hasIce":0,"x":1.8,"y":-0.20000029,"angle":270,"scaleX":0.2421875,"scaleY":0.45,"polygonColliderPoints":[{"x":-2.4363685,"y":0.53999996},{"x":-2.5511053,"y":0.40401322},{"x":-2.5498672,"y":-0.37077624},{"x":-2.43151,"y":-0.53592014},{"x":2.4284582,"y":-0.47191802},{"x":2.4913006,"y":-0.449712},{"x":2.5158255,"y":-0.36324117},{"x":2.5351708,"y":0.40336686},{"x":2.5016344,"y":0.4714166},{"x":2.4345713,"y":0.5232619}]},{"id":35,"layer":5,"layerPhysic":16,"orderLayer":13,"spriteName":"bar","hasIce":0,"x":-1.5000043,"y":0.11499834,"angle":2.862151,"scaleX":0.2423327,"scaleY":0.4500001,"polygonColliderPoints":[{"x":-2.4363685,"y":0.53999996},{"x":-2.5511053,"y":0.40401322},{"x":-2.5498672,"y":-0.37077624},{"x":-2.43151,"y":-0.53592014},{"x":2.4284582,"y":-0.47191802},{"x":2.4913006,"y":-0.449712},{"x":2.5158255,"y":-0.36324117},{"x":2.5351708,"y":0.40336686},{"x":2.5016344,"y":0.4714166},{"x":2.4345713,"y":0.5232619}]},{"id":36,"layer":5,"layerPhysic":16,"orderLayer":13,"spriteName":"bar","hasIce":0,"x":1.5000029,"y":0.114997864,"angle":357.1379,"scaleX":0.242333,"scaleY":0.4500001,"polygonColliderPoints":[{"x":-2.4363685,"y":0.53999996},{"x":-2.5511053,"y":0.40401322},{"x":-2.5498672,"y":-0.37077624},{"x":-2.43151,"y":-0.53592014},{"x":2.4284582,"y":-0.47191802},{"x":2.4913006,"y":-0.449712},{"x":2.5158255,"y":-0.36324117},{"x":2.5351708,"y":0.40336686},{"x":2.5016344,"y":0.4714166},{"x":2.4345713,"y":0.5232619}]},{"id":37,"layer":7,"layerPhysic":18,"orderLayer":17,"spriteName":"Solid_Circle_1","hasIce":0,"x":-1.7999997,"y":-0.5,"angle":0,"scaleX":0.6499999,"scaleY":0.6499999,"polygonColliderPoints":[{"x":0.45552891,"y":0.26812398},{"x":0.3846335,"y":0.3621542},{"x":0.2676116,"y":0.4560413},{"x":0.15078515,"y":0.51051235},{"x":0.07539319,"y":0.5340945},{"x":-0.18079714,"y":0.4932123},{"x":-0.31760857,"y":0.41321233},{"x":-0.42961335,"y":0.28480673},{"x":-0.48798552,"y":0.19400842},{"x":-0.5256038,"y":0.019637242},{"x":-0.51120764,"y":-0.13920286},{"x":-0.42840573,"y":-0.2932124},{"x":-0.30359903,"y":-0.42241523},{"x":-0.16519332,"y":-0.4932124},{"x":-0.07105205,"y":-0.5066472},{"x":0.15041047,"y":-0.46442005},{"x":0.30881616,"y":-0.39722195},{"x":0.46801904,"y":-0.2323914},{"x":0.52180284,"y":-0.07864271},{"x":0.5148066,"y":0.08123149}]},{"id":38,"layer":7,"layerPhysic":18,"orderLayer":17,"spriteName":"Solid_Circle_1","hasIce":0,"x":1.8,"y":-0.5,"angle":0,"scaleX":0.6499999,"scaleY":0.6499999,"polygonColliderPoints":[{"x":0.45552891,"y":0.26812398},{"x":0.3846335,"y":0.3621542},{"x":0.2676116,"y":0.4560413},{"x":0.15078515,"y":0.51051235},{"x":0.07539319,"y":0.5340945},{"x":-0.18079714,"y":0.4932123},{"x":-0.31760857,"y":0.41321233},{"x":-0.42961335,"y":0.28480673},{"x":-0.48798552,"y":0.19400842},{"x":-0.5256038,"y":0.019637242},{"x":-0.51120764,"y":-0.13920286},{"x":-0.42840573,"y":-0.2932124},{"x":-0.30359903,"y":-0.42241523},{"x":-0.16519332,"y":-0.4932124},{"x":-0.07105205,"y":-0.5066472},{"x":0.15041047,"y":-0.46442005},{"x":0.30881616,"y":-0.39722195},{"x":0.46801904,"y":-0.2323914},{"x":0.52180284,"y":-0.07864271},{"x":0.5148066,"y":0.08123149}]},{"id":39,"layer":3,"layerPhysic":14,"orderLayer":9,"spriteName":"bar","hasIce":0,"x":-9.536743e-7,"y":-0.44000626,"angle":-0.00004967385,"scaleX":0.3398449,"scaleY":0.45,"polygonColliderPoints":[{"x":-2.4363685,"y":0.53999996},{"x":-2.5511053,"y":0.40401322},{"x":-2.5498672,"y":-0.37077624},{"x":-2.43151,"y":-0.53592014},{"x":2.4284582,"y":-0.47191802},{"x":2.4913006,"y":-0.449712},{"x":2.5158255,"y":-0.36324117},{"x":2.5351708,"y":0.40336686},{"x":2.5016344,"y":0.4714166},{"x":2.4345713,"y":0.5232619}]},{"id":40,"layer":8,"layerPhysic":19,"orderLayer":19,"spriteName":"silver 2","hasIce":0,"x":1.400002,"y":-1.450005,"angle":147.995,"scaleX":0.2886776,"scaleY":0.45,"polygonColliderPoints":[{"x":-2.4363685,"y":0.53999996},{"x":-2.5511053,"y":0.40401322},{"x":-2.5498672,"y":-0.37077624},{"x":-2.43151,"y":-0.53592014},{"x":2.4284582,"y":-0.47191802},{"x":2.4913006,"y":-0.449712},{"x":2.5158255,"y":-0.36324117},{"x":2.5351708,"y":0.40336686},{"x":2.5016344,"y":0.4714166},{"x":2.4345713,"y":0.5232619}]},{"id":41,"layer":8,"layerPhysic":19,"orderLayer":19,"spriteName":"silver 2","hasIce":0,"x":-1.4000039,"y":-1.4500041,"angle":32.00518,"scaleX":0.2886773,"scaleY":0.4499999,"polygonColliderPoints":[{"x":-2.4363685,"y":0.53999996},{"x":-2.5511053,"y":0.40401322},{"x":-2.5498672,"y":-0.37077624},{"x":-2.43151,"y":-0.53592014},{"x":2.4284582,"y":-0.47191802},{"x":2.4913006,"y":-0.449712},{"x":2.5158255,"y":-0.36324117},{"x":2.5351708,"y":0.40336686},{"x":2.5016344,"y":0.4714166},{"x":2.4345713,"y":0.5232619}]},{"id":42,"layer":9,"layerPhysic":20,"orderLayer":21,"spriteName":"bar","hasIce":0,"x":-1.2999997,"y":-1.8000002,"angle":168.6901,"scaleX":0.3039608,"scaleY":0.4499999,"polygonColliderPoints":[{"x":-2.4363685,"y":0.53999996},{"x":-2.5511053,"y":0.40401322},{"x":-2.5498672,"y":-0.37077624},{"x":-2.43151,"y":-0.53592014},{"x":2.4284582,"y":-0.47191802},{"x":2.4913006,"y":-0.449712},{"x":2.5158255,"y":-0.36324117},{"x":2.5351708,"y":0.40336686},{"x":2.5016344,"y":0.4714166},{"x":2.4345713,"y":0.5232619}]},{"id":43,"layer":9,"layerPhysic":20,"orderLayer":21,"spriteName":"bar","hasIce":0,"x":1.3,"y":-1.8000002,"angle":191.3099,"scaleX":0.3039608,"scaleY":0.4499999,"polygonColliderPoints":[{"x":-2.4363685,"y":0.53999996},{"x":-2.5511053,"y":0.40401322},{"x":-2.5498672,"y":-0.37077624},{"x":-2.43151,"y":-0.53592014},{"x":2.4284582,"y":-0.47191802},{"x":2.4913006,"y":-0.449712},{"x":2.5158255,"y":-0.36324117},{"x":2.5351708,"y":0.40336686},{"x":2.5016344,"y":0.4714166},{"x":2.4345713,"y":0.5232619}]},{"id":44,"layer":7,"layerPhysic":18,"orderLayer":17,"spriteName":"bar","hasIce":0,"x":-0.9000039,"y":-1.550004,"angle":105.946205,"scaleX":0.245601,"scaleY":0.45,"polygonColliderPoints":[{"x":-2.4363685,"y":0.53999996},{"x":-2.5511053,"y":0.40401322},{"x":-2.5498672,"y":-0.37077624},{"x":-2.43151,"y":-0.53592014},{"x":2.4284582,"y":-0.47191802},{"x":2.4913006,"y":-0.449712},{"x":2.5158255,"y":-0.36324117},{"x":2.5351708,"y":0.40336686},{"x":2.5016344,"y":0.4714166},{"x":2.4345713,"y":0.5232619}]},{"id":45,"layer":5,"layerPhysic":16,"orderLayer":13,"spriteName":"bar","hasIce":0,"x":0.9000025,"y":-1.550005,"angle":74.053986,"scaleX":0.2456004,"scaleY":0.45,"polygonColliderPoints":[{"x":-2.4363685,"y":0.53999996},{"x":-2.5511053,"y":0.40401322},{"x":-2.5498672,"y":-0.37077624},{"x":-2.43151,"y":-0.53592014},{"x":2.4284582,"y":-0.47191802},{"x":2.4913006,"y":-0.449712},{"x":2.5158255,"y":-0.36324117},{"x":2.5351708,"y":0.40336686},{"x":2.5016344,"y":0.4714166},{"x":2.4345713,"y":0.5232619}]},{"id":46,"layer":5,"layerPhysic":16,"orderLayer":13,"spriteName":"bar","hasIce":0,"x":-0.40000057,"y":-1.6500053,"angle":32.00486,"scaleX":0.2886782,"scaleY":0.45,"polygonColliderPoints":[{"x":-2.4363685,"y":0.53999996},{"x":-2.5511053,"y":0.40401322},{"x":-2.5498672,"y":-0.37077624},{"x":-2.43151,"y":-0.53592014},{"x":2.4284582,"y":-0.47191802},{"x":2.4913006,"y":-0.449712},{"x":2.5158255,"y":-0.36324117},{"x":2.5351708,"y":0.40336686},{"x":2.5016344,"y":0.4714166},{"x":2.4345713,"y":0.5232619}]},{"id":47,"layer":7,"layerPhysic":18,"orderLayer":17,"spriteName":"bar","hasIce":0,"x":0.39999938,"y":-1.6500053,"angle":147.9952,"scaleX":0.2886786,"scaleY":0.45,"polygonColliderPoints":[{"x":-2.4363685,"y":0.53999996},{"x":-2.5511053,"y":0.40401322},{"x":-2.5498672,"y":-0.37077624},{"x":-2.43151,"y":-0.53592014},{"x":2.4284582,"y":-0.47191802},{"x":2.4913006,"y":-0.449712},{"x":2.5158255,"y":-0.36324117},{"x":2.5351708,"y":0.40336686},{"x":2.5016344,"y":0.4714166},{"x":2.4345713,"y":0.5232619}]},{"id":48,"layer":4,"layerPhysic":15,"orderLayer":11,"spriteName":"bar","hasIce":0,"x":0,"y":-1.8999996,"angle":180,"scaleX":0.42,"scaleY":0.45,"polygonColliderPoints":[{"x":-2.4363685,"y":0.53999996},{"x":-2.5511053,"y":0.40401322},{"x":-2.5498672,"y":-0.37077624},{"x":-2.43151,"y":-0.53592014},{"x":2.4284582,"y":-0.47191802},{"x":2.4913006,"y":-0.449712},{"x":2.5158255,"y":-0.36324117},{"x":2.5351708,"y":0.40336686},{"x":2.5016344,"y":0.4714166},{"x":2.4345713,"y":0.5232619}]},{"id":49,"layer":4,"layerPhysic":15,"orderLayer":11,"spriteName":"bar","hasIce":0,"x":-1.4000039,"y":-0.8500047,"angle":138.8134,"scaleX":0.3126028,"scaleY":0.45,"polygonColliderPoints":[{"x":-2.4363685,"y":0.53999996},{"x":-2.5511053,"y":0.40401322},{"x":-2.5498672,"y":-0.37077624},{"x":-2.43151,"y":-0.53592014},{"x":2.4284582,"y":-0.47191802},{"x":2.4913006,"y":-0.449712},{"x":2.5158255,"y":-0.36324117},{"x":2.5351708,"y":0.40336686},{"x":2.5016344,"y":0.4714166},{"x":2.4345713,"y":0.5232619}]},{"id":50,"layer":2,"layerPhysic":7,"orderLayer":7,"spriteName":"bar","hasIce":0,"x":1.400002,"y":-0.8500056,"angle":221.1865,"scaleX":0.3126036,"scaleY":0.45,"polygonColliderPoints":[{"x":-2.485,"y":0.53999996},{"x":-2.565,"y":0.48},{"x":-2.565,"y":-0.53999996},{"x":2.565,"y":-0.53999996},{"x":2.565,"y":0.53},{"x":2.5349998,"y":0.53999996}]},{"id":51,"layer":4,"layerPhysic":15,"orderLayer":11,"spriteName":"bar","hasIce":0,"x":4.7683716e-7,"y":1.9750051,"angle":89.99997,"scaleX":0.4100019,"scaleY":0.45,"polygonColliderPoints":[{"x":-2.4363685,"y":0.53999996},{"x":-2.5511053,"y":0.40401322},{"x":-2.5498672,"y":-0.37077624},{"x":-2.43151,"y":-0.53592014},{"x":2.4284582,"y":-0.47191802},{"x":2.4913006,"y":-0.449712},{"x":2.5158255,"y":-0.36324117},{"x":2.5351708,"y":0.40336686},{"x":2.5016344,"y":0.4714166},{"x":2.4345713,"y":0.5232619}]}],"time":180}]}