{"level":702,"steps":[{"holeModels":[{"id":0,"hasScrew":1,"hasLock":0,"hasAdsHole":0,"hasIce":0,"hasKey":0,"screwPoolType":0,"hasLockKey":0,"x":-0.3000002,"y":-1.0999999,"scaleX":0.4,"scaleY":0.4,"iceUnlockNumber":0,"hasLockNumberScrew":0,"numberLockIron":0},{"id":1,"hasScrew":1,"hasLock":0,"hasAdsHole":0,"hasIce":0,"hasKey":0,"screwPoolType":0,"hasLockKey":0,"x":0.5,"y":-1.1000009,"scaleX":0.4,"scaleY":0.4,"iceUnlockNumber":0,"hasLockNumberScrew":0,"numberLockIron":0},{"id":2,"hasScrew":1,"hasLock":0,"hasAdsHole":0,"hasIce":0,"hasKey":0,"screwPoolType":0,"hasLockKey":0,"x":-0.5,"y":0.3000002,"scaleX":0.4,"scaleY":0.4,"iceUnlockNumber":0,"hasLockNumberScrew":0,"numberLockIron":0},{"id":3,"hasScrew":1,"hasLock":0,"hasAdsHole":0,"hasIce":0,"hasKey":0,"screwPoolType":0,"hasLockKey":0,"x":0.29999995,"y":0.2999997,"scaleX":0.4,"scaleY":0.4,"iceUnlockNumber":0,"hasLockNumberScrew":0,"numberLockIron":0},{"id":4,"hasScrew":1,"hasLock":0,"hasAdsHole":0,"hasIce":0,"hasKey":0,"screwPoolType":0,"hasLockKey":0,"x":1.0999999,"y":-0.3000002,"scaleX":0.4,"scaleY":0.4,"iceUnlockNumber":0,"hasLockNumberScrew":0,"numberLockIron":0},{"id":5,"hasScrew":1,"hasLock":0,"hasAdsHole":0,"hasIce":0,"hasKey":0,"screwPoolType":0,"hasLockKey":0,"x":-1.1000009,"y":-0.3000002,"scaleX":0.4,"scaleY":0.4,"iceUnlockNumber":0,"hasLockNumberScrew":0,"numberLockIron":0},{"id":6,"hasScrew":1,"hasLock":0,"hasAdsHole":0,"hasIce":0,"hasKey":0,"screwPoolType":0,"hasLockKey":0,"x":-0.4000001,"y":0.9000001,"scaleX":0.4,"scaleY":0.4,"iceUnlockNumber":0,"hasLockNumberScrew":0,"numberLockIron":0},{"id":7,"hasScrew":1,"hasLock":0,"hasAdsHole":0,"hasIce":0,"hasKey":0,"screwPoolType":0,"hasLockKey":0,"x":0.20000005,"y":0.9000001,"scaleX":0.4,"scaleY":0.4,"iceUnlockNumber":0,"hasLockNumberScrew":0,"numberLockIron":0},{"id":8,"hasScrew":0,"hasLock":0,"hasAdsHole":1,"hasIce":0,"hasKey":0,"screwPoolType":0,"hasLockKey":0,"x":0,"y":2.5,"scaleX":0.4,"scaleY":0.4,"iceUnlockNumber":0,"hasLockNumberScrew":0,"numberLockIron":0},{"id":9,"hasScrew":0,"hasLock":0,"hasAdsHole":0,"hasIce":0,"hasKey":0,"screwPoolType":0,"hasLockKey":0,"x":-0.8000002,"y":2.5,"scaleX":0.4,"scaleY":0.4,"iceUnlockNumber":0,"hasLockNumberScrew":0,"numberLockIron":0},{"id":10,"hasScrew":0,"hasLock":0,"hasAdsHole":0,"hasIce":0,"hasKey":0,"screwPoolType":0,"hasLockKey":0,"x":0.8000002,"y":2.5,"scaleX":0.4,"scaleY":0.4,"iceUnlockNumber":0,"hasLockNumberScrew":0,"numberLockIron":0},{"id":11,"hasScrew":0,"hasLock":0,"hasAdsHole":0,"hasIce":0,"hasKey":0,"screwPoolType":0,"hasLockKey":0,"x":0.4000001,"y":1.5,"scaleX":0.4,"scaleY":0.4,"iceUnlockNumber":0,"hasLockNumberScrew":0,"numberLockIron":0}],"itemBoomModels":[],"keyModels":[],"ironOverlayModels":[],"itemRopeModels":[],"boardIncreaseSize":0,"ironModels":[{"id":0,"layer":2,"layerPhysic":7,"orderLayer":7,"spriteName":"bar","hasIce":0,"x":-0.4000001,"y":-0.4000001,"angle":278.13007,"scaleX":0.4012141,"scaleY":0.4500003,"polygonColliderPoints":[{"x":-2.4363685,"y":0.53999996},{"x":-2.5511053,"y":0.40401322},{"x":-2.5498672,"y":-0.37077624},{"x":-2.43151,"y":-0.53592014},{"x":2.4284582,"y":-0.47191802},{"x":2.4913006,"y":-0.449712},{"x":2.5158255,"y":-0.36324117},{"x":2.5351708,"y":0.40336686},{"x":2.5016344,"y":0.4714166},{"x":2.4345713,"y":0.5232619}]},{"id":1,"layer":2,"layerPhysic":7,"orderLayer":7,"spriteName":"bar","hasIce":0,"x":0.4000001,"y":-0.4000001,"angle":278.13007,"scaleX":0.4012141,"scaleY":0.4500003,"polygonColliderPoints":[{"x":-2.4363685,"y":0.53999996},{"x":-2.5511053,"y":0.40401322},{"x":-2.5498672,"y":-0.37077624},{"x":-2.43151,"y":-0.53592014},{"x":2.4284582,"y":-0.47191802},{"x":2.4913006,"y":-0.449712},{"x":2.5158255,"y":-0.36324117},{"x":2.5351708,"y":0.40336686},{"x":2.5016344,"y":0.4714166},{"x":2.4345713,"y":0.5232619}]},{"id":2,"layer":1,"layerPhysic":6,"orderLayer":5,"spriteName":"bar","hasIce":0,"x":-0.8000002,"y":0,"angle":224.99998,"scaleX":0.2907281,"scaleY":0.4499995,"polygonColliderPoints":[{"x":-2.4363685,"y":0.53999996},{"x":-2.5511053,"y":0.40401322},{"x":-2.5498672,"y":-0.37077624},{"x":-2.4434211,"y":-0.5248026},{"x":2.4376051,"y":-0.51033485},{"x":2.5034964,"y":-0.46678618},{"x":2.543266,"y":-0.39738947},{"x":2.5504155,"y":0.3948298},{"x":2.5016344,"y":0.4714166},{"x":2.4345713,"y":0.5232619}]},{"id":3,"layer":1,"layerPhysic":6,"orderLayer":5,"spriteName":"bar","hasIce":0,"x":0.70000005,"y":-4.7683716e-7,"angle":323.1301,"scaleX":0.3203126,"scaleY":0.4500001,"polygonColliderPoints":[{"x":-2.4363685,"y":0.53999996},{"x":-2.5511053,"y":0.40401322},{"x":-2.5498672,"y":-0.37077624},{"x":-2.4434211,"y":-0.5248026},{"x":2.4376051,"y":-0.51033485},{"x":2.5034964,"y":-0.46678618},{"x":2.543266,"y":-0.39738947},{"x":2.5504155,"y":0.3948298},{"x":2.5016344,"y":0.4714166},{"x":2.4345713,"y":0.5232619}]},{"id":4,"layer":3,"layerPhysic":14,"orderLayer":9,"spriteName":"bar","hasIce":0,"x":0,"y":-0.3000002,"angle":0,"scaleX":0.5546876,"scaleY":0.45,"polygonColliderPoints":[{"x":-2.4363685,"y":0.53999996},{"x":-2.5511053,"y":0.40401322},{"x":-2.5498672,"y":-0.37077624},{"x":-2.43151,"y":-0.53592014},{"x":2.4284582,"y":-0.47191802},{"x":2.4913006,"y":-0.449712},{"x":2.5158255,"y":-0.36324117},{"x":2.5351708,"y":0.40336686},{"x":2.5016344,"y":0.4714166},{"x":2.4345713,"y":0.5232619}]},{"id":5,"layer":3,"layerPhysic":14,"orderLayer":9,"spriteName":"bar","hasIce":0,"x":-0.2249999,"y":0.2999997,"angle":0,"scaleX":0.35625,"scaleY":0.45,"polygonColliderPoints":[{"x":-2.4363685,"y":0.53999996},{"x":-2.5511053,"y":0.40401322},{"x":-2.5498672,"y":-0.37077624},{"x":-2.43151,"y":-0.53592014},{"x":2.4284582,"y":-0.47191802},{"x":2.4913006,"y":-0.449712},{"x":2.5158255,"y":-0.36324117},{"x":2.5351708,"y":0.40336686},{"x":2.5016344,"y":0.4714166},{"x":2.4345713,"y":0.5232619}]},{"id":6,"layer":3,"layerPhysic":14,"orderLayer":9,"spriteName":"bar","hasIce":0,"x":0.2249999,"y":-1.0999999,"angle":0,"scaleX":0.35625,"scaleY":0.45,"polygonColliderPoints":[{"x":-2.4363685,"y":0.53999996},{"x":-2.5511053,"y":0.40401322},{"x":-2.5498672,"y":-0.37077624},{"x":-2.43151,"y":-0.53592014},{"x":2.4284582,"y":-0.47191802},{"x":2.4913006,"y":-0.449712},{"x":2.5158255,"y":-0.36324117},{"x":2.5351708,"y":0.40336686},{"x":2.5016344,"y":0.4714166},{"x":2.4345713,"y":0.5232619}]},{"id":7,"layer":6,"layerPhysic":17,"orderLayer":15,"spriteName":"shape (19)","hasIce":0,"x":-0.099999905,"y":1.125,"angle":0,"scaleX":0.45,"scaleY":0.45,"polygonColliderPoints":[{"x":0.57,"y":-1.4599999},{"x":0.83,"y":-1.3},{"x":1.18,"y":-0.85999995},{"x":1.31,"y":-0.42999998},{"x":1.29,"y":0.04},{"x":1.38,"y":0.049999997},{"x":1.74,"y":0.32999998},{"x":1.87,"y":0.64},{"x":1.8199999,"y":1.1},{"x":1.61,"y":1.41},{"x":1.27,"y":1.5699999},{"x":0.78,"y":1.53},{"x":0.65,"y":1.4599999},{"x":0.56,"y":1.4},{"x":0.32,"y":1.02},{"x":0.16,"y":1.04},{"x":0.02,"y":1.05},{"x":-0.16,"y":1.04},{"x":-0.32,"y":1.01},{"x":-0.35999998,"y":1.11},{"x":-0.42999998,"y":1.24},{"x":-0.78999996,"y":1.54},{"x":-0.89,"y":1.5699999},{"x":-1.3299999,"y":1.5699999},{"x":-1.54,"y":1.4699999},{"x":-1.8399999,"y":1.11},{"x":-1.87,"y":0.58},{"x":-1.76,"y":0.35999998},{"x":-1.63,"y":0.21},{"x":-1.3199999,"y":0.03},{"x":-1.31,"y":-0.04},{"x":-1.3299999,"y":-0.25},{"x":-1.1899999,"y":-0.84999996},{"x":-0.96999997,"y":-1.17},{"x":-0.58,"y":-1.4699999},{"x":-0.42999998,"y":-1.53},{"x":0.24,"y":-1.5699999}]}],"time":60},{"holeModels":[{"id":0,"hasScrew":1,"hasLock":0,"hasAdsHole":0,"hasIce":0,"hasKey":0,"screwPoolType":0,"hasLockKey":0,"x":0,"y":2.85,"scaleX":0.4,"scaleY":0.4,"iceUnlockNumber":0,"hasLockNumberScrew":0,"numberLockIron":0},{"id":1,"hasScrew":1,"hasLock":0,"hasAdsHole":0,"hasIce":0,"hasKey":0,"screwPoolType":0,"hasLockKey":0,"x":-0.8000002,"y":2.6,"scaleX":0.4,"scaleY":0.4,"iceUnlockNumber":0,"hasLockNumberScrew":0,"numberLockIron":0},{"id":2,"hasScrew":1,"hasLock":0,"hasAdsHole":0,"hasIce":0,"hasKey":0,"screwPoolType":0,"hasLockKey":0,"x":0.79999995,"y":2.6,"scaleX":0.4,"scaleY":0.4,"iceUnlockNumber":0,"hasLockNumberScrew":0,"numberLockIron":0},{"id":3,"hasScrew":1,"hasLock":0,"hasAdsHole":0,"hasIce":0,"hasKey":0,"screwPoolType":0,"hasLockKey":0,"x":-1.5,"y":2.1999998,"scaleX":0.4,"scaleY":0.4,"iceUnlockNumber":0,"hasLockNumberScrew":0,"numberLockIron":0},{"id":4,"hasScrew":1,"hasLock":0,"hasAdsHole":0,"hasIce":0,"hasKey":0,"screwPoolType":0,"hasLockKey":0,"x":1.5,"y":2.1999998,"scaleX":0.4,"scaleY":0.4,"iceUnlockNumber":0,"hasLockNumberScrew":0,"numberLockIron":0},{"id":5,"hasScrew":1,"hasLock":0,"hasAdsHole":0,"hasIce":0,"hasKey":0,"screwPoolType":0,"hasLockKey":0,"x":-0.625,"y":1.875,"scaleX":0.4,"scaleY":0.4,"iceUnlockNumber":0,"hasLockNumberScrew":0,"numberLockIron":0},{"id":6,"hasScrew":1,"hasLock":0,"hasAdsHole":0,"hasIce":0,"hasKey":0,"screwPoolType":0,"hasLockKey":0,"x":0.625,"y":1.875,"scaleX":0.4,"scaleY":0.4,"iceUnlockNumber":0,"hasLockNumberScrew":0,"numberLockIron":0},{"id":7,"hasScrew":1,"hasLock":0,"hasAdsHole":0,"hasIce":0,"hasKey":0,"screwPoolType":0,"hasLockKey":0,"x":-1.1749997,"y":1.3000002,"scaleX":0.4,"scaleY":0.4,"iceUnlockNumber":0,"hasLockNumberScrew":0,"numberLockIron":0},{"id":8,"hasScrew":1,"hasLock":0,"hasAdsHole":0,"hasIce":0,"hasKey":0,"screwPoolType":0,"hasLockKey":0,"x":1.175,"y":1.3000002,"scaleX":0.4,"scaleY":0.4,"iceUnlockNumber":0,"hasLockNumberScrew":0,"numberLockIron":0},{"id":9,"hasScrew":1,"hasLock":0,"hasAdsHole":0,"hasIce":0,"hasKey":0,"screwPoolType":0,"hasLockKey":0,"x":-0.3249998,"y":0.625,"scaleX":0.4,"scaleY":0.4,"iceUnlockNumber":0,"hasLockNumberScrew":0,"numberLockIron":0},{"id":10,"hasScrew":1,"hasLock":0,"hasAdsHole":0,"hasIce":0,"hasKey":0,"screwPoolType":0,"hasLockKey":0,"x":0.32500005,"y":0.625,"scaleX":0.4,"scaleY":0.4,"iceUnlockNumber":0,"hasLockNumberScrew":0,"numberLockIron":0},{"id":11,"hasScrew":1,"hasLock":0,"hasAdsHole":0,"hasIce":0,"hasKey":0,"screwPoolType":0,"hasLockKey":0,"x":-0.4000001,"y":1.3000002,"scaleX":0.4,"scaleY":0.4,"iceUnlockNumber":0,"hasLockNumberScrew":0,"numberLockIron":0},{"id":12,"hasScrew":1,"hasLock":0,"hasAdsHole":0,"hasIce":0,"hasKey":0,"screwPoolType":0,"hasLockKey":0,"x":-1.7999997,"y":-1.6999998,"scaleX":0.4,"scaleY":0.4,"iceUnlockNumber":0,"hasLockNumberScrew":0,"numberLockIron":0},{"id":13,"hasScrew":1,"hasLock":0,"hasAdsHole":0,"hasIce":0,"hasKey":0,"screwPoolType":0,"hasLockKey":0,"x":1.8,"y":-1.6999998,"scaleX":0.4,"scaleY":0.4,"iceUnlockNumber":0,"hasLockNumberScrew":0,"numberLockIron":0},{"id":14,"hasScrew":1,"hasLock":0,"hasAdsHole":0,"hasIce":0,"hasKey":0,"screwPoolType":0,"hasLockKey":0,"x":-1,"y":-1.6999998,"scaleX":0.4,"scaleY":0.4,"iceUnlockNumber":0,"hasLockNumberScrew":0,"numberLockIron":0},{"id":15,"hasScrew":1,"hasLock":0,"hasAdsHole":0,"hasIce":0,"hasKey":0,"screwPoolType":0,"hasLockKey":0,"x":1,"y":-1.7000008,"scaleX":0.4,"scaleY":0.4,"iceUnlockNumber":0,"hasLockNumberScrew":0,"numberLockIron":0},{"id":16,"hasScrew":1,"hasLock":0,"hasAdsHole":0,"hasIce":0,"hasKey":0,"screwPoolType":0,"hasLockKey":0,"x":0,"y":-1.6999998,"scaleX":0.4,"scaleY":0.4,"iceUnlockNumber":0,"hasLockNumberScrew":0,"numberLockIron":0},{"id":17,"hasScrew":1,"hasLock":0,"hasAdsHole":0,"hasIce":0,"hasKey":0,"screwPoolType":0,"hasLockKey":0,"x":-1.1749997,"y":-0.6999998,"scaleX":0.4,"scaleY":0.4,"iceUnlockNumber":0,"hasLockNumberScrew":0,"numberLockIron":0},{"id":18,"hasScrew":1,"hasLock":0,"hasAdsHole":0,"hasIce":0,"hasKey":0,"screwPoolType":0,"hasLockKey":0,"x":1.175,"y":-0.6999998,"scaleX":0.4,"scaleY":0.4,"iceUnlockNumber":0,"hasLockNumberScrew":0,"numberLockIron":0},{"id":19,"hasScrew":1,"hasLock":0,"hasAdsHole":0,"hasIce":0,"hasKey":0,"screwPoolType":0,"hasLockKey":0,"x":-1.1749997,"y":0.625,"scaleX":0.4,"scaleY":0.4,"iceUnlockNumber":0,"hasLockNumberScrew":0,"numberLockIron":0},{"id":20,"hasScrew":1,"hasLock":0,"hasAdsHole":0,"hasIce":0,"hasKey":0,"screwPoolType":0,"hasLockKey":0,"x":1.175,"y":0.625,"scaleX":0.4,"scaleY":0.4,"iceUnlockNumber":0,"hasLockNumberScrew":0,"numberLockIron":0},{"id":21,"hasScrew":1,"hasLock":0,"hasAdsHole":0,"hasIce":0,"hasKey":0,"screwPoolType":0,"hasLockKey":0,"x":-1.7999997,"y":-0.099999905,"scaleX":0.4,"scaleY":0.4,"iceUnlockNumber":0,"hasLockNumberScrew":0,"numberLockIron":0},{"id":22,"hasScrew":1,"hasLock":0,"hasAdsHole":0,"hasIce":0,"hasKey":0,"screwPoolType":0,"hasLockKey":0,"x":1.8,"y":-0.099999905,"scaleX":0.4,"scaleY":0.4,"iceUnlockNumber":0,"hasLockNumberScrew":0,"numberLockIron":0},{"id":23,"hasScrew":1,"hasLock":0,"hasAdsHole":0,"hasIce":0,"hasKey":0,"screwPoolType":0,"hasLockKey":0,"x":-1.7999997,"y":0.9000001,"scaleX":0.4,"scaleY":0.4,"iceUnlockNumber":0,"hasLockNumberScrew":0,"numberLockIron":0},{"id":24,"hasScrew":1,"hasLock":0,"hasAdsHole":0,"hasIce":0,"hasKey":0,"screwPoolType":0,"hasLockKey":0,"x":1.8,"y":0.9000001,"scaleX":0.4,"scaleY":0.4,"iceUnlockNumber":0,"hasLockNumberScrew":0,"numberLockIron":0},{"id":25,"hasScrew":0,"hasLock":0,"hasAdsHole":0,"hasIce":0,"hasKey":0,"screwPoolType":0,"hasLockKey":0,"x":-1.7999997,"y":3.3,"scaleX":0.4,"scaleY":0.4,"iceUnlockNumber":0,"hasLockNumberScrew":0,"numberLockIron":0},{"id":26,"hasScrew":0,"hasLock":0,"hasAdsHole":0,"hasIce":0,"hasKey":0,"screwPoolType":0,"hasLockKey":0,"x":-1.7999997,"y":2.7,"scaleX":0.4,"scaleY":0.4,"iceUnlockNumber":0,"hasLockNumberScrew":0,"numberLockIron":0},{"id":27,"hasScrew":0,"hasLock":0,"hasAdsHole":0,"hasIce":0,"hasKey":0,"screwPoolType":0,"hasLockKey":0,"x":1.8,"y":2.7,"scaleX":0.4,"scaleY":0.4,"iceUnlockNumber":0,"hasLockNumberScrew":0,"numberLockIron":0},{"id":28,"hasScrew":0,"hasLock":0,"hasAdsHole":1,"hasIce":0,"hasKey":0,"screwPoolType":0,"hasLockKey":0,"x":1.8,"y":3.3,"scaleX":0.4,"scaleY":0.4,"iceUnlockNumber":0,"hasLockNumberScrew":0,"numberLockIron":0},{"id":29,"hasScrew":1,"hasLock":0,"hasAdsHole":0,"hasIce":1,"hasKey":0,"screwPoolType":0,"hasLockKey":0,"x":0,"y":-0.6999998,"scaleX":0.4,"scaleY":0.4,"iceUnlockNumber":0,"hasLockNumberScrew":0,"numberLockIron":0},{"id":30,"hasScrew":1,"hasLock":0,"hasAdsHole":0,"hasIce":0,"hasKey":0,"screwPoolType":0,"hasLockKey":0,"x":0.4000001,"y":1.3000002,"scaleX":0.4,"scaleY":0.4,"iceUnlockNumber":0,"hasLockNumberScrew":0,"numberLockIron":0}],"itemBoomModels":[],"keyModels":[],"ironOverlayModels":[],"itemRopeModels":[],"boardIncreaseSize":0.08,"ironModels":[{"id":0,"layer":6,"layerPhysic":17,"orderLayer":15,"spriteName":"shape (39)","hasIce":0,"x":-1.2000003,"y":1.9000001,"angle":45.000004,"scaleX":0.45,"scaleY":0.45,"polygonColliderPoints":[{"x":-0.11,"y":-1.1999999},{"x":0.03,"y":-1.1999999},{"x":1.01,"y":-1.6899999},{"x":1.24,"y":-1.6899999},{"x":1.37,"y":-1.63},{"x":1.5799999,"y":-1.35},{"x":1.5799999,"y":-1.0799999},{"x":0.25,"y":1.65},{"x":0.16,"y":1.6899999},{"x":-0.17,"y":1.6899999},{"x":-0.28,"y":1.63},{"x":-1.5799999,"y":-1.09},{"x":-1.5699999,"y":-1.4},{"x":-1.49,"y":-1.52},{"x":-1.4,"y":-1.62},{"x":-1.26,"y":-1.6899999},{"x":-0.97999996,"y":-1.6899999}]},{"id":1,"layer":6,"layerPhysic":17,"orderLayer":15,"spriteName":"shape (39)","hasIce":0,"x":1.2,"y":1.9000001,"angle":315,"scaleX":0.45,"scaleY":0.45,"polygonColliderPoints":[{"x":-0.11,"y":-1.1999999},{"x":0.03,"y":-1.1999999},{"x":1.01,"y":-1.6899999},{"x":1.24,"y":-1.6899999},{"x":1.37,"y":-1.63},{"x":1.5799999,"y":-1.35},{"x":1.5799999,"y":-1.0799999},{"x":0.25,"y":1.65},{"x":0.16,"y":1.6899999},{"x":-0.17,"y":1.6899999},{"x":-0.28,"y":1.63},{"x":-1.5799999,"y":-1.09},{"x":-1.5699999,"y":-1.4},{"x":-1.49,"y":-1.52},{"x":-1.4,"y":-1.62},{"x":-1.26,"y":-1.6899999},{"x":-0.97999996,"y":-1.6899999}]},{"id":2,"layer":8,"layerPhysic":19,"orderLayer":19,"spriteName":"shape (34)","hasIce":0,"x":0,"y":1.3000002,"angle":0,"scaleX":0.45,"scaleY":0.45,"polygonColliderPoints":[{"x":1.8299999,"y":-0.695},{"x":1.81,"y":-0.345},{"x":1.56,"y":0.16499999},{"x":1.09,"y":0.645},{"x":0.65999997,"y":0.85499996},{"x":0.34,"y":0.945},{"x":0.31,"y":0.955},{"x":-0.55,"y":0.905},{"x":-0.95,"y":0.72499996},{"x":-1.4699999,"y":0.295},{"x":-1.76,"y":-0.185},{"x":-1.8299999,"y":-0.385},{"x":-1.8299999,"y":-0.73499995},{"x":-1.7199999,"y":-0.895},{"x":-1.61,"y":-0.92499995},{"x":1.61,"y":-0.92499995},{"x":1.7199999,"y":-0.865}]},{"id":3,"layer":7,"layerPhysic":18,"orderLayer":17,"spriteName":"shape (28)","hasIce":0,"x":0,"y":0.59000015,"angle":224.99998,"scaleX":0.45,"scaleY":0.45,"polygonColliderPoints":[{"x":0.995,"y":-0.275},{"x":0.695,"y":0.265},{"x":0.125,"y":0.79499996},{"x":-0.655,"y":1.095},{"x":-1.025,"y":1.095},{"x":-1.095,"y":1.045},{"x":-1.0849999,"y":-0.225},{"x":-1.035,"y":-0.275},{"x":-0.935,"y":-0.305},{"x":-0.765,"y":-0.345},{"x":-0.575,"y":-0.465},{"x":-0.39499998,"y":-0.675},{"x":-0.345,"y":-0.78499997},{"x":-0.305,"y":-0.995},{"x":-0.225,"y":-1.095},{"x":1.035,"y":-1.095},{"x":1.095,"y":-1.005},{"x":1.0849999,"y":-0.575}]},{"id":4,"layer":4,"layerPhysic":15,"orderLayer":11,"spriteName":"bar","hasIce":0,"x":-1.0625,"y":-0.5374999,"angle":237.6086,"scaleX":0.6377748,"scaleY":0.45,"polygonColliderPoints":[{"x":-2.4363685,"y":0.53999996},{"x":-2.5511053,"y":0.40401322},{"x":-2.5498672,"y":-0.37077624},{"x":-2.43151,"y":-0.53592014},{"x":2.4284582,"y":-0.47191802},{"x":2.4913006,"y":-0.449712},{"x":2.5158255,"y":-0.36324117},{"x":2.5351708,"y":0.40336686},{"x":2.5016344,"y":0.4714166},{"x":2.4345713,"y":0.5232619}]},{"id":5,"layer":4,"layerPhysic":15,"orderLayer":11,"spriteName":"bar","hasIce":0,"x":1.0625,"y":-0.5374999,"angle":302.3914,"scaleX":0.6627748,"scaleY":0.45,"polygonColliderPoints":[{"x":-2.4363685,"y":0.53999996},{"x":-2.5511053,"y":0.40401322},{"x":-2.5498672,"y":-0.37077624},{"x":-2.43151,"y":-0.53592014},{"x":2.4284582,"y":-0.47191802},{"x":2.4913006,"y":-0.449712},{"x":2.5158255,"y":-0.36324117},{"x":2.5351708,"y":0.40336686},{"x":2.5016344,"y":0.4714166},{"x":2.4345713,"y":0.5232619}]},{"id":6,"layer":3,"layerPhysic":14,"orderLayer":9,"spriteName":"bar","hasIce":0,"x":-0.1624999,"y":-0.037499905,"angle":283.78156,"scaleX":0.3914602,"scaleY":0.45,"polygonColliderPoints":[{"x":-2.4363685,"y":0.53999996},{"x":-2.5511053,"y":0.40401322},{"x":-2.5498672,"y":-0.37077624},{"x":-2.43151,"y":-0.53592014},{"x":2.4284582,"y":-0.47191802},{"x":2.4913006,"y":-0.449712},{"x":2.5158255,"y":-0.36324117},{"x":2.5351708,"y":0.40336686},{"x":2.5016344,"y":0.4714166},{"x":2.4345713,"y":0.5232619}]},{"id":7,"layer":2,"layerPhysic":7,"orderLayer":7,"spriteName":"bar","hasIce":0,"x":0.1624999,"y":-0.037499905,"angle":76.2184,"scaleX":0.3914602,"scaleY":0.45,"polygonColliderPoints":[{"x":-2.4363685,"y":0.53999996},{"x":-2.5511053,"y":0.40401322},{"x":-2.5498672,"y":-0.37077624},{"x":-2.43151,"y":-0.53592014},{"x":2.4284582,"y":-0.47191802},{"x":2.4913006,"y":-0.449712},{"x":2.5158255,"y":-0.36324117},{"x":2.5351708,"y":0.40336686},{"x":2.5016344,"y":0.4714166},{"x":2.4345713,"y":0.5232619}]},{"id":8,"layer":5,"layerPhysic":16,"orderLayer":13,"spriteName":"bar","hasIce":0,"x":-1.1749997,"y":0.3000002,"angle":270,"scaleX":0.515625,"scaleY":0.45,"polygonColliderPoints":[{"x":-2.4363685,"y":0.53999996},{"x":-2.5511053,"y":0.40401322},{"x":-2.5498672,"y":-0.37077624},{"x":-2.43151,"y":-0.53592014},{"x":2.4284582,"y":-0.47191802},{"x":2.4913006,"y":-0.449712},{"x":2.5158255,"y":-0.36324117},{"x":2.5351708,"y":0.40336686},{"x":2.5016344,"y":0.4714166},{"x":2.4345713,"y":0.5232619}]},{"id":9,"layer":5,"layerPhysic":16,"orderLayer":13,"spriteName":"bar","hasIce":0,"x":1.175,"y":0.3000002,"angle":90,"scaleX":0.515625,"scaleY":0.45,"polygonColliderPoints":[{"x":-2.4363685,"y":0.53999996},{"x":-2.5511053,"y":0.40401322},{"x":-2.5498672,"y":-0.37077624},{"x":-2.43151,"y":-0.53592014},{"x":2.4284582,"y":-0.47191802},{"x":2.4913006,"y":-0.449712},{"x":2.5158255,"y":-0.36324117},{"x":2.5351708,"y":0.40336686},{"x":2.5016344,"y":0.4714166},{"x":2.4345713,"y":0.5232619}]},{"id":10,"layer":6,"layerPhysic":17,"orderLayer":15,"spriteName":"bar","hasIce":0,"x":0,"y":-1.6999998,"angle":-0.00001366038,"scaleX":0.5156251,"scaleY":0.45,"polygonColliderPoints":[{"x":-2.4363685,"y":0.53999996},{"x":-2.5511053,"y":0.40401322},{"x":-2.5498672,"y":-0.37077624},{"x":-2.43151,"y":-0.53592014},{"x":2.4284582,"y":-0.47191802},{"x":2.4913006,"y":-0.449712},{"x":2.5158255,"y":-0.36324117},{"x":2.5351708,"y":0.40336686},{"x":2.5016344,"y":0.4714166},{"x":2.4345713,"y":0.5232619}]},{"id":11,"layer":6,"layerPhysic":17,"orderLayer":15,"spriteName":"bar","hasIce":0,"x":-1.7999997,"y":-0.4000001,"angle":90,"scaleX":0.6328123,"scaleY":0.45,"polygonColliderPoints":[{"x":-2.4363685,"y":0.53999996},{"x":-2.5511053,"y":0.40401322},{"x":-2.5498672,"y":-0.37077624},{"x":-2.43151,"y":-0.53592014},{"x":2.4284582,"y":-0.47191802},{"x":2.4913006,"y":-0.449712},{"x":2.5158255,"y":-0.36324117},{"x":2.5351708,"y":0.40336686},{"x":2.5016344,"y":0.4714166},{"x":2.4345713,"y":0.5232619}]},{"id":12,"layer":6,"layerPhysic":17,"orderLayer":15,"spriteName":"bar","hasIce":0,"x":1.8,"y":-0.4000001,"angle":270,"scaleX":0.6328123,"scaleY":0.45,"polygonColliderPoints":[{"x":-2.4363685,"y":0.53999996},{"x":-2.5511053,"y":0.40401322},{"x":-2.5498672,"y":-0.37077624},{"x":-2.43151,"y":-0.53592014},{"x":2.4284582,"y":-0.47191802},{"x":2.4913006,"y":-0.449712},{"x":2.5158255,"y":-0.36324117},{"x":2.5351708,"y":0.40336686},{"x":2.5016344,"y":0.4714166},{"x":2.4345713,"y":0.5232619}]},{"id":13,"layer":2,"layerPhysic":7,"orderLayer":7,"spriteName":"bar","hasIce":0,"x":-1.4874997,"y":-0.4000001,"angle":316.1692,"scaleX":0.2942161,"scaleY":0.45,"polygonColliderPoints":[{"x":-2.4363685,"y":0.53999996},{"x":-2.5511053,"y":0.40401322},{"x":-2.5498672,"y":-0.37077624},{"x":-2.43151,"y":-0.53592014},{"x":2.4284582,"y":-0.47191802},{"x":2.4913006,"y":-0.449712},{"x":2.5158255,"y":-0.36324117},{"x":2.5351708,"y":0.40336686},{"x":2.5016344,"y":0.4714166},{"x":2.4345713,"y":0.5232619}]},{"id":14,"layer":2,"layerPhysic":7,"orderLayer":7,"spriteName":"bar","hasIce":0,"x":1.4875,"y":-0.4000001,"angle":43.83085,"scaleX":0.2942161,"scaleY":0.45,"polygonColliderPoints":[{"x":-2.4363685,"y":0.53999996},{"x":-2.5511053,"y":0.40401322},{"x":-2.5498672,"y":-0.37077624},{"x":-2.43151,"y":-0.53592014},{"x":2.4284582,"y":-0.47191802},{"x":2.4913006,"y":-0.449712},{"x":2.5158255,"y":-0.36324117},{"x":2.5351708,"y":0.40336686},{"x":2.5016344,"y":0.4714166},{"x":2.4345713,"y":0.5232619}]},{"id":15,"layer":3,"layerPhysic":14,"orderLayer":9,"spriteName":"bar","hasIce":0,"x":-1.4874997,"y":0.2624998,"angle":49.236404,"scaleX":0.286955,"scaleY":0.45,"polygonColliderPoints":[{"x":-2.4363685,"y":0.53999996},{"x":-2.5511053,"y":0.40401322},{"x":-2.5498672,"y":-0.37077624},{"x":-2.43151,"y":-0.53592014},{"x":2.4284582,"y":-0.47191802},{"x":2.4913006,"y":-0.449712},{"x":2.5158255,"y":-0.36324117},{"x":2.5351708,"y":0.40336686},{"x":2.5016344,"y":0.4714166},{"x":2.4345713,"y":0.5232619}]},{"id":16,"layer":3,"layerPhysic":14,"orderLayer":9,"spriteName":"bar","hasIce":0,"x":1.4875,"y":0.2624998,"angle":130.7636,"scaleX":0.286955,"scaleY":0.45,"polygonColliderPoints":[{"x":-2.4363685,"y":0.53999996},{"x":-2.5511053,"y":0.40401322},{"x":-2.5498672,"y":-0.37077624},{"x":-2.43151,"y":-0.53592014},{"x":2.4284582,"y":-0.47191802},{"x":2.4913006,"y":-0.449712},{"x":2.5158255,"y":-0.36324117},{"x":2.5351708,"y":0.40336686},{"x":2.5016344,"y":0.4714166},{"x":2.4345713,"y":0.5232619}]},{"id":17,"layer":1,"layerPhysic":6,"orderLayer":5,"spriteName":"bar","hasIce":0,"x":-0.75,"y":0.625,"angle":180,"scaleX":0.2660156,"scaleY":0.45,"polygonColliderPoints":[{"x":-2.4363685,"y":0.53999996},{"x":-2.5511053,"y":0.40401322},{"x":-2.5498672,"y":-0.37077624},{"x":-2.4434211,"y":-0.5248026},{"x":2.4376051,"y":-0.51033485},{"x":2.5034964,"y":-0.46678618},{"x":2.543266,"y":-0.39738947},{"x":2.5504155,"y":0.3948298},{"x":2.5016344,"y":0.4714166},{"x":2.4345713,"y":0.5232619}]},{"id":18,"layer":1,"layerPhysic":6,"orderLayer":5,"spriteName":"bar","hasIce":0,"x":0.75,"y":0.625,"angle":0,"scaleX":0.2660156,"scaleY":0.45,"polygonColliderPoints":[{"x":-2.4363685,"y":0.53999996},{"x":-2.5511053,"y":0.40401322},{"x":-2.5498672,"y":-0.37077624},{"x":-2.4434211,"y":-0.5248026},{"x":2.4376051,"y":-0.51033485},{"x":2.5034964,"y":-0.46678618},{"x":2.543266,"y":-0.39738947},{"x":2.5504155,"y":0.3948298},{"x":2.5016344,"y":0.4714166},{"x":2.4345713,"y":0.5232619}]},{"id":19,"layer":7,"layerPhysic":18,"orderLayer":17,"spriteName":"bar","hasIce":0,"x":-1.4000001,"y":-1.6999998,"angle":0,"scaleX":0.28125,"scaleY":0.45,"polygonColliderPoints":[{"x":-2.4363685,"y":0.53999996},{"x":-2.5511053,"y":0.40401322},{"x":-2.5498672,"y":-0.37077624},{"x":-2.43151,"y":-0.53592014},{"x":2.4284582,"y":-0.47191802},{"x":2.4913006,"y":-0.449712},{"x":2.5158255,"y":-0.36324117},{"x":2.5351708,"y":0.40336686},{"x":2.5016344,"y":0.4714166},{"x":2.4345713,"y":0.5232619}]},{"id":20,"layer":7,"layerPhysic":18,"orderLayer":17,"spriteName":"bar","hasIce":0,"x":1.4000001,"y":-1.6999998,"angle":0.00003415096,"scaleX":0.2812499,"scaleY":0.45,"polygonColliderPoints":[{"x":-2.4363685,"y":0.53999996},{"x":-2.5511053,"y":0.40401322},{"x":-2.5498672,"y":-0.37077624},{"x":-2.43151,"y":-0.53592014},{"x":2.4284582,"y":-0.47191802},{"x":2.4913006,"y":-0.449712},{"x":2.5158255,"y":-0.36324117},{"x":2.5351708,"y":0.40336686},{"x":2.5016344,"y":0.4714166},{"x":2.4345713,"y":0.5232619}]},{"id":21,"layer":3,"layerPhysic":14,"orderLayer":9,"spriteName":"bar","hasIce":0,"x":-1.0875001,"y":-1.1999998,"angle":279.9262,"scaleX":0.3232807,"scaleY":0.45,"polygonColliderPoints":[{"x":-2.4363685,"y":0.53999996},{"x":-2.5511053,"y":0.40401322},{"x":-2.5498672,"y":-0.37077624},{"x":-2.43151,"y":-0.53592014},{"x":2.4284582,"y":-0.47191802},{"x":2.4913006,"y":-0.449712},{"x":2.5158255,"y":-0.36324117},{"x":2.5351708,"y":0.40336686},{"x":2.5016344,"y":0.4714166},{"x":2.4345713,"y":0.5232619}]},{"id":22,"layer":3,"layerPhysic":14,"orderLayer":9,"spriteName":"bar","hasIce":0,"x":1.0875001,"y":-1.1999998,"angle":260.0738,"scaleX":0.3232808,"scaleY":0.45,"polygonColliderPoints":[{"x":-2.4363685,"y":0.53999996},{"x":-2.5511053,"y":0.40401322},{"x":-2.5498672,"y":-0.37077624},{"x":-2.43151,"y":-0.53592014},{"x":2.4284582,"y":-0.47191802},{"x":2.4913006,"y":-0.449712},{"x":2.5158255,"y":-0.36324117},{"x":2.5351708,"y":0.40336686},{"x":2.5016344,"y":0.4714166},{"x":2.4345713,"y":0.5232619}]},{"id":23,"layer":4,"layerPhysic":15,"orderLayer":11,"spriteName":"bar","hasIce":0,"x":-0.5,"y":-1.1999998,"angle":224.99998,"scaleX":0.4012136,"scaleY":0.45,"polygonColliderPoints":[{"x":-2.4363685,"y":0.53999996},{"x":-2.5511053,"y":0.40401322},{"x":-2.5498672,"y":-0.37077624},{"x":-2.43151,"y":-0.53592014},{"x":2.4284582,"y":-0.47191802},{"x":2.4913006,"y":-0.449712},{"x":2.5158255,"y":-0.36324117},{"x":2.5351708,"y":0.40336686},{"x":2.5016344,"y":0.4714166},{"x":2.4345713,"y":0.5232619}]},{"id":24,"layer":1,"layerPhysic":6,"orderLayer":5,"spriteName":"bar","hasIce":0,"x":0.5,"y":-1.1999998,"angle":315,"scaleX":0.4012137,"scaleY":0.45,"polygonColliderPoints":[{"x":-2.4363685,"y":0.53999996},{"x":-2.5511053,"y":0.40401322},{"x":-2.5498672,"y":-0.37077624},{"x":-2.4434211,"y":-0.5248026},{"x":2.4376051,"y":-0.51033485},{"x":2.5034964,"y":-0.46678618},{"x":2.543266,"y":-0.39738947},{"x":2.5504155,"y":0.3948298},{"x":2.5016344,"y":0.4714166},{"x":2.4345713,"y":0.5232619}]},{"id":25,"layer":5,"layerPhysic":16,"orderLayer":13,"spriteName":"bar","hasIce":0,"x":0,"y":-1.1999998,"angle":270,"scaleX":0.3203125,"scaleY":0.45,"polygonColliderPoints":[{"x":-2.4363685,"y":0.53999996},{"x":-2.5511053,"y":0.40401322},{"x":-2.5498672,"y":-0.37077624},{"x":-2.43151,"y":-0.53592014},{"x":2.4284582,"y":-0.47191802},{"x":2.4913006,"y":-0.449712},{"x":2.5158255,"y":-0.36324117},{"x":2.5351708,"y":0.40336686},{"x":2.5016344,"y":0.4714166},{"x":2.4345713,"y":0.5232619}]},{"id":26,"layer":9,"layerPhysic":20,"orderLayer":21,"spriteName":"bar","hasIce":0,"x":0,"y":-0.6999998,"angle":0,"scaleX":0.5839843,"scaleY":0.45,"polygonColliderPoints":[{"x":-2.4363685,"y":0.53999996},{"x":-2.5511053,"y":0.40401322},{"x":-2.5498672,"y":-0.37077624},{"x":-2.43151,"y":-0.53592014},{"x":2.4284582,"y":-0.47191802},{"x":2.4913006,"y":-0.449712},{"x":2.5158255,"y":-0.36324117},{"x":2.5351708,"y":0.40336686},{"x":2.5016344,"y":0.4714166},{"x":2.4345713,"y":0.5232619}]},{"id":27,"layer":1,"layerPhysic":6,"orderLayer":5,"spriteName":"bar","hasIce":0,"x":-0.5875001,"y":-1.1999998,"angle":319.6001,"scaleX":0.426353,"scaleY":0.45,"polygonColliderPoints":[{"x":-2.4363685,"y":0.53999996},{"x":-2.5511053,"y":0.40401322},{"x":-2.5498672,"y":-0.37077624},{"x":-2.4434211,"y":-0.5248026},{"x":2.4376051,"y":-0.51033485},{"x":2.5034964,"y":-0.46678618},{"x":2.543266,"y":-0.39738947},{"x":2.5504155,"y":0.3948298},{"x":2.5016344,"y":0.4714166},{"x":2.4345713,"y":0.5232619}]},{"id":28,"layer":8,"layerPhysic":19,"orderLayer":19,"spriteName":"silver 2","hasIce":0,"x":0.5875001,"y":-1.1999998,"angle":40.39991,"scaleX":0.4255219,"scaleY":0.45,"polygonColliderPoints":[{"x":-2.4363685,"y":0.53999996},{"x":-2.5511053,"y":0.40401322},{"x":-2.5498672,"y":-0.37077624},{"x":-2.43151,"y":-0.53592014},{"x":2.4284582,"y":-0.47191802},{"x":2.4913006,"y":-0.449712},{"x":2.5158255,"y":-0.36324117},{"x":2.5351708,"y":0.40336686},{"x":2.5016344,"y":0.4714166},{"x":2.4345713,"y":0.5232619}]},{"id":29,"layer":2,"layerPhysic":7,"orderLayer":7,"spriteName":"bar","hasIce":0,"x":-1.4874997,"y":0.7624998,"angle":156.2505,"scaleX":0.2583643,"scaleY":0.45,"polygonColliderPoints":[{"x":-2.4363685,"y":0.53999996},{"x":-2.5511053,"y":0.40401322},{"x":-2.5498672,"y":-0.37077624},{"x":-2.43151,"y":-0.53592014},{"x":2.4284582,"y":-0.47191802},{"x":2.4913006,"y":-0.449712},{"x":2.5158255,"y":-0.36324117},{"x":2.5351708,"y":0.40336686},{"x":2.5016344,"y":0.4714166},{"x":2.4345713,"y":0.5232619}]},{"id":30,"layer":2,"layerPhysic":7,"orderLayer":7,"spriteName":"bar","hasIce":0,"x":1.4875,"y":0.7624998,"angle":23.749493,"scaleX":0.2583643,"scaleY":0.45,"polygonColliderPoints":[{"x":-2.4363685,"y":0.53999996},{"x":-2.5511053,"y":0.40401322},{"x":-2.5498672,"y":-0.37077624},{"x":-2.43151,"y":-0.53592014},{"x":2.4284582,"y":-0.47191802},{"x":2.4913006,"y":-0.449712},{"x":2.5158255,"y":-0.36324117},{"x":2.5351708,"y":0.40336686},{"x":2.5016344,"y":0.4714166},{"x":2.4345713,"y":0.5232619}]},{"id":31,"layer":8,"layerPhysic":19,"orderLayer":19,"spriteName":"silver 2","hasIce":0,"x":-0.5875001,"y":-0.037499905,"angle":131.5664,"scaleX":0.46997,"scaleY":0.45,"polygonColliderPoints":[{"x":-2.4363685,"y":0.53999996},{"x":-2.5511053,"y":0.40401322},{"x":-2.5498672,"y":-0.37077624},{"x":-2.43151,"y":-0.53592014},{"x":2.4284582,"y":-0.47191802},{"x":2.4913006,"y":-0.449712},{"x":2.5158255,"y":-0.36324117},{"x":2.5351708,"y":0.40336686},{"x":2.5016344,"y":0.4714166},{"x":2.4345713,"y":0.5232619}]},{"id":32,"layer":7,"layerPhysic":18,"orderLayer":17,"spriteName":"bar","hasIce":0,"x":0.5875001,"y":-0.037499905,"angle":48.43364,"scaleX":0.4708879,"scaleY":0.45,"polygonColliderPoints":[{"x":-2.4363685,"y":0.53999996},{"x":-2.5511053,"y":0.40401322},{"x":-2.5498672,"y":-0.37077624},{"x":-2.43151,"y":-0.53592014},{"x":2.4284582,"y":-0.47191802},{"x":2.4913006,"y":-0.449712},{"x":2.5158255,"y":-0.36324117},{"x":2.5351708,"y":0.40336686},{"x":2.5016344,"y":0.4714166},{"x":2.4345713,"y":0.5232619}]},{"id":33,"layer":1,"layerPhysic":6,"orderLayer":5,"spriteName":"bar","hasIce":0,"x":-1.6500001,"y":1.5500002,"angle":257.0054,"scaleX":0.3605794,"scaleY":0.45,"polygonColliderPoints":[{"x":-2.4363685,"y":0.53999996},{"x":-2.5511053,"y":0.40401322},{"x":-2.5498672,"y":-0.37077624},{"x":-2.4434211,"y":-0.5248026},{"x":2.4376051,"y":-0.51033485},{"x":2.5034964,"y":-0.46678618},{"x":2.543266,"y":-0.39738947},{"x":2.5504155,"y":0.3948298},{"x":2.5016344,"y":0.4714166},{"x":2.4345713,"y":0.5232619}]},{"id":34,"layer":1,"layerPhysic":6,"orderLayer":5,"spriteName":"bar","hasIce":0,"x":1.6500001,"y":1.5500002,"angle":282.9946,"scaleX":0.3605794,"scaleY":0.45,"polygonColliderPoints":[{"x":-2.4363685,"y":0.53999996},{"x":-2.5511053,"y":0.40401322},{"x":-2.5498672,"y":-0.37077624},{"x":-2.4434211,"y":-0.5248026},{"x":2.4376051,"y":-0.51033485},{"x":2.5034964,"y":-0.46678618},{"x":2.543266,"y":-0.39738947},{"x":2.5504155,"y":0.3948298},{"x":2.5016344,"y":0.4714166},{"x":2.4345713,"y":0.5232619}]},{"id":35,"layer":4,"layerPhysic":15,"orderLayer":11,"spriteName":"bar","hasIce":0,"x":-1.4874997,"y":1.0999999,"angle":212.6192,"scaleX":0.2699299,"scaleY":0.45,"polygonColliderPoints":[{"x":-2.4363685,"y":0.53999996},{"x":-2.5511053,"y":0.40401322},{"x":-2.5498672,"y":-0.37077624},{"x":-2.43151,"y":-0.53592014},{"x":2.4284582,"y":-0.47191802},{"x":2.4913006,"y":-0.449712},{"x":2.5158255,"y":-0.36324117},{"x":2.5351708,"y":0.40336686},{"x":2.5016344,"y":0.4714166},{"x":2.4345713,"y":0.5232619}]},{"id":36,"layer":4,"layerPhysic":15,"orderLayer":11,"spriteName":"bar","hasIce":0,"x":1.4875,"y":1.0999999,"angle":327.38068,"scaleX":0.2699299,"scaleY":0.45,"polygonColliderPoints":[{"x":-2.4363685,"y":0.53999996},{"x":-2.5511053,"y":0.40401322},{"x":-2.5498672,"y":-0.37077624},{"x":-2.43151,"y":-0.53592014},{"x":2.4284582,"y":-0.47191802},{"x":2.4913006,"y":-0.449712},{"x":2.5158255,"y":-0.36324117},{"x":2.5351708,"y":0.40336686},{"x":2.5016344,"y":0.4714166},{"x":2.4345713,"y":0.5232619}]},{"id":37,"layer":2,"layerPhysic":7,"orderLayer":7,"spriteName":"bar","hasIce":0,"x":-1.1500001,"y":2.4,"angle":209.7449,"scaleX":0.282466,"scaleY":0.45,"polygonColliderPoints":[{"x":-2.4363685,"y":0.53999996},{"x":-2.5511053,"y":0.40401322},{"x":-2.5498672,"y":-0.37077624},{"x":-2.43151,"y":-0.53592014},{"x":2.4284582,"y":-0.47191802},{"x":2.4913006,"y":-0.449712},{"x":2.5158255,"y":-0.36324117},{"x":2.5351708,"y":0.40336686},{"x":2.5016344,"y":0.4714166},{"x":2.4345713,"y":0.5232619}]},{"id":38,"layer":2,"layerPhysic":7,"orderLayer":7,"spriteName":"bar","hasIce":0,"x":1.1500001,"y":2.4,"angle":330.2551,"scaleX":0.282466,"scaleY":0.45,"polygonColliderPoints":[{"x":-2.4363685,"y":0.53999996},{"x":-2.5511053,"y":0.40401322},{"x":-2.5498672,"y":-0.37077624},{"x":-2.43151,"y":-0.53592014},{"x":2.4284582,"y":-0.47191802},{"x":2.4913006,"y":-0.449712},{"x":2.5158255,"y":-0.36324117},{"x":2.5351708,"y":0.40336686},{"x":2.5016344,"y":0.4714166},{"x":2.4345713,"y":0.5232619}]},{"id":39,"layer":1,"layerPhysic":6,"orderLayer":5,"spriteName":"bar","hasIce":0,"x":-0.7125001,"y":2.2375002,"angle":283.5704,"scaleX":0.2456683,"scaleY":0.45,"polygonColliderPoints":[{"x":-2.4363685,"y":0.53999996},{"x":-2.5511053,"y":0.40401322},{"x":-2.5498672,"y":-0.37077624},{"x":-2.4434211,"y":-0.5248026},{"x":2.4376051,"y":-0.51033485},{"x":2.5034964,"y":-0.46678618},{"x":2.543266,"y":-0.39738947},{"x":2.5504155,"y":0.3948298},{"x":2.5016344,"y":0.4714166},{"x":2.4345713,"y":0.5232619}]},{"id":40,"layer":1,"layerPhysic":6,"orderLayer":5,"spriteName":"bar","hasIce":0,"x":0.7125001,"y":2.2375002,"angle":256.4296,"scaleX":0.2456683,"scaleY":0.45,"polygonColliderPoints":[{"x":-2.4363685,"y":0.53999996},{"x":-2.5511053,"y":0.40401322},{"x":-2.5498672,"y":-0.37077624},{"x":-2.4434211,"y":-0.5248026},{"x":2.4376051,"y":-0.51033485},{"x":2.5034964,"y":-0.46678618},{"x":2.543266,"y":-0.39738947},{"x":2.5504155,"y":0.3948298},{"x":2.5016344,"y":0.4714166},{"x":2.4345713,"y":0.5232619}]},{"id":41,"layer":7,"layerPhysic":18,"orderLayer":17,"spriteName":"shape (29)","hasIce":0,"x":0,"y":2.62,"angle":45.000004,"scaleX":0.45,"scaleY":0.45,"polygonColliderPoints":[{"x":1.9549999,"y":-1.745},{"x":1.935,"y":-1.305},{"x":1.745,"y":-0.565},{"x":1.665,"y":-0.375},{"x":1.615,"y":-0.265},{"x":1.3249999,"y":0.255},{"x":0.965,"y":0.705},{"x":0.555,"y":1.095},{"x":-0.074999996,"y":1.525},{"x":-0.815,"y":1.8249999},{"x":-1.435,"y":1.9549999},{"x":-1.745,"y":1.9549999},{"x":-1.805,"y":1.935},{"x":-1.885,"y":1.895},{"x":-1.9449999,"y":1.8349999},{"x":-1.9549999,"y":1.805},{"x":-1.935,"y":0.685},{"x":-1.775,"y":0.555},{"x":-1.495,"y":0.525},{"x":-0.865,"y":0.33499998},{"x":-0.195,"y":-0.13499999},{"x":0.325,"y":-0.865},{"x":0.575,"y":-1.8249999},{"x":0.685,"y":-1.9449999},{"x":0.715,"y":-1.9549999},{"x":1.8449999,"y":-1.935},{"x":1.895,"y":-1.875},{"x":1.935,"y":-1.805}]},{"id":42,"layer":4,"layerPhysic":15,"orderLayer":11,"spriteName":"bar","hasIce":0,"x":-0.5124998,"y":1.5875001,"angle":291.3706,"scaleX":0.2205966,"scaleY":0.45,"polygonColliderPoints":[{"x":-2.4363685,"y":0.53999996},{"x":-2.5511053,"y":0.40401322},{"x":-2.5498672,"y":-0.37077624},{"x":-2.43151,"y":-0.53592014},{"x":2.4284582,"y":-0.47191802},{"x":2.4913006,"y":-0.449712},{"x":2.5158255,"y":-0.36324117},{"x":2.5351708,"y":0.40336686},{"x":2.5016344,"y":0.4714166},{"x":2.4345713,"y":0.5232619}]},{"id":43,"layer":4,"layerPhysic":15,"orderLayer":11,"spriteName":"bar","hasIce":0,"x":0.51250005,"y":1.5875001,"angle":248.6294,"scaleX":0.2205966,"scaleY":0.45,"polygonColliderPoints":[{"x":-2.4363685,"y":0.53999996},{"x":-2.5511053,"y":0.40401322},{"x":-2.5498672,"y":-0.37077624},{"x":-2.43151,"y":-0.53592014},{"x":2.4284582,"y":-0.47191802},{"x":2.4913006,"y":-0.449712},{"x":2.5158255,"y":-0.36324117},{"x":2.5351708,"y":0.40336686},{"x":2.5016344,"y":0.4714166},{"x":2.4345713,"y":0.5232619}]},{"id":44,"layer":2,"layerPhysic":7,"orderLayer":7,"spriteName":"bar","hasIce":0,"x":0,"y":1.875,"angle":0,"scaleX":0.3441406,"scaleY":0.45,"polygonColliderPoints":[{"x":-2.485,"y":0.53999996},{"x":-2.565,"y":0.48},{"x":-2.565,"y":-0.53999996},{"x":2.565,"y":-0.53999996},{"x":2.565,"y":0.53},{"x":2.5349998,"y":0.53999996}]},{"id":45,"layer":3,"layerPhysic":14,"orderLayer":9,"spriteName":"bar","hasIce":0,"x":-0.7874999,"y":1.3000002,"angle":0,"scaleX":0.2763672,"scaleY":0.45,"polygonColliderPoints":[{"x":-2.4363685,"y":0.53999996},{"x":-2.5511053,"y":0.40401322},{"x":-2.5498672,"y":-0.37077624},{"x":-2.43151,"y":-0.53592014},{"x":2.4284582,"y":-0.47191802},{"x":2.4913006,"y":-0.449712},{"x":2.5158255,"y":-0.36324117},{"x":2.5351708,"y":0.40336686},{"x":2.5016344,"y":0.4714166},{"x":2.4345713,"y":0.5232619}]},{"id":46,"layer":3,"layerPhysic":14,"orderLayer":9,"spriteName":"bar","hasIce":0,"x":0.7874999,"y":1.3000002,"angle":180,"scaleX":0.2763672,"scaleY":0.45,"polygonColliderPoints":[{"x":-2.4363685,"y":0.53999996},{"x":-2.5511053,"y":0.40401322},{"x":-2.5498672,"y":-0.37077624},{"x":-2.43151,"y":-0.53592014},{"x":2.4284582,"y":-0.47191802},{"x":2.4913006,"y":-0.449712},{"x":2.5158255,"y":-0.36324117},{"x":2.5351708,"y":0.40336686},{"x":2.5016344,"y":0.4714166},{"x":2.4345713,"y":0.5232619}]}],"time":180}]}